<?xml version="1.0" encoding="UTF-8" standalone="yes"?>
<trk>
    <name>Moregallo, Corni di Canzo, Malascarpa, Prasanto, Cornizzolo, Rai, Birone 1939</name>
    <trkseg>
        <trkpt lat="45.850218599662185" lon="9.35150588862598">
            <ele>320.74</ele>
            <time>2018-04-22T05:00:28Z</time>
        </trkpt>
        <trkpt lat="45.85063258185983" lon="9.35089417733252">
            <ele>336.6</ele>
            <time>2018-04-22T05:04:11Z</time>
        </trkpt>
        <trkpt lat="45.850794687867165" lon="9.350209459662437">
            <ele>348.62</ele>
            <time>2018-04-22T05:05:17Z</time>
        </trkpt>
        <trkpt lat="45.85167093202472" lon="9.351242361590266">
            <ele>369.76</ele>
            <time>2018-04-22T05:07:26Z</time>
        </trkpt>
        <trkpt lat="45.85172885097563" lon="9.350707679986954">
            <ele>377.94</ele>
            <time>2018-04-22T05:08:41Z</time>
        </trkpt>
        <trkpt lat="45.85287080146372" lon="9.350350610911846">
            <ele>401.01</ele>
            <time>2018-04-22T05:11:21Z</time>
        </trkpt>
        <trkpt lat="45.85375710390508" lon="9.350567199289799">
            <ele>413.02</ele>
            <time>2018-04-22T05:13:19Z</time>
        </trkpt>
        <trkpt lat="45.854705264791846" lon="9.34928853996098">
            <ele>440.42</ele>
            <time>2018-04-22T05:16:28Z</time>
        </trkpt>
        <trkpt lat="45.85462152957916" lon="9.349010679870844">
            <ele>450.03</ele>
            <time>2018-04-22T05:17:25Z</time>
        </trkpt>
        <trkpt lat="45.8547595795244" lon="9.348151870071888">
            <ele>467.82</ele>
            <time>2018-04-22T05:19:14Z</time>
        </trkpt>
        <trkpt lat="45.85528696887195" lon="9.34753437526524">
            <ele>491.85</ele>
            <time>2018-04-22T05:21:31Z</time>
        </trkpt>
        <trkpt lat="45.85548008792102" lon="9.346920317038894">
            <ele>506.27</ele>
            <time>2018-04-22T05:22:52Z</time>
        </trkpt>
        <trkpt lat="45.855787536129355" lon="9.346778243780136">
            <ele>518.77</ele>
            <time>2018-04-22T05:24:00Z</time>
        </trkpt>
        <trkpt lat="45.8558854367584" lon="9.345690691843629">
            <ele>545.69</ele>
            <time>2018-04-22T05:26:37Z</time>
        </trkpt>
        <trkpt lat="45.85622121579945" lon="9.345316020771861">
            <ele>566.83</ele>
            <time>2018-04-22T05:28:45Z</time>
        </trkpt>
        <trkpt lat="45.85614058189094" lon="9.345113094896078">
            <ele>574.04</ele>
            <time>2018-04-22T05:29:27Z</time>
        </trkpt>
        <trkpt lat="45.856837537139654" lon="9.344328548759222">
            <ele>609.13</ele>
            <time>2018-04-22T05:33:04Z</time>
        </trkpt>
        <trkpt lat="45.857249423861504" lon="9.344163425266743">
            <ele>621.15</ele>
            <time>2018-04-22T05:34:20Z</time>
        </trkpt>
        <trkpt lat="45.85759718902409" lon="9.34358767233789">
            <ele>635.09</ele>
            <time>2018-04-22T05:35:51Z</time>
        </trkpt>
        <trkpt lat="45.85829833522439" lon="9.343175366520882">
            <ele>660.56</ele>
            <time>2018-04-22T05:38:22Z</time>
        </trkpt>
        <trkpt lat="45.85929066874087" lon="9.343784898519516">
            <ele>679.31</ele>
            <time>2018-04-22T05:41:19Z</time>
        </trkpt>
        <trkpt lat="45.859811352565885" lon="9.343461440876126">
            <ele>691.33</ele>
            <time>2018-04-22T05:43:00Z</time>
        </trkpt>
        <trkpt lat="45.86003640666604" lon="9.342093346640468">
            <ele>711.51</ele>
            <time>2018-04-22T05:45:34Z</time>
        </trkpt>
        <trkpt lat="45.86030161008239" lon="9.341627480462193">
            <ele>726.41</ele>
            <time>2018-04-22T05:47:13Z</time>
        </trkpt>
        <trkpt lat="45.860175378620625" lon="9.34149395674467">
            <ele>729.3</ele>
            <time>2018-04-22T05:49:06Z</time>
        </trkpt>
        <trkpt lat="45.860438821837306" lon="9.341918332502246">
            <ele>734.1</ele>
            <time>2018-04-22T05:51:42Z</time>
        </trkpt>
        <trkpt lat="45.860619116574526" lon="9.341822108253837">
            <ele>744.2</ele>
            <time>2018-04-22T05:52:35Z</time>
        </trkpt>
        <trkpt lat="45.86075892671943" lon="9.342039786279202">
            <ele>755.25</ele>
            <time>2018-04-22T05:53:44Z</time>
        </trkpt>
        <trkpt lat="45.86087526753545" lon="9.341905424371362">
            <ele>763.42</ele>
            <time>2018-04-22T05:54:35Z</time>
        </trkpt>
        <trkpt lat="45.8613458275795" lon="9.342269115149975">
            <ele>784.09</ele>
            <time>2018-04-22T05:56:48Z</time>
        </trkpt>
        <trkpt lat="45.86158596910536" lon="9.342799857258797">
            <ele>801.88</ele>
            <time>2018-04-22T05:58:36Z</time>
        </trkpt>
        <trkpt lat="45.861823512241244" lon="9.34282835572958">
            <ele>812.45</ele>
            <time>2018-04-22T06:00:36Z</time>
        </trkpt>
        <trkpt lat="45.86205644533038" lon="9.343404024839401">
            <ele>842.73</ele>
            <time>2018-04-22T06:05:05Z</time>
        </trkpt>
        <trkpt lat="45.86250403895974" lon="9.343528412282467">
            <ele>871.09</ele>
            <time>2018-04-22T06:07:59Z</time>
        </trkpt>
        <trkpt lat="45.862649381160736" lon="9.344104584306479">
            <ele>906.18</ele>
            <time>2018-04-22T06:11:46Z</time>
        </trkpt>
        <trkpt lat="45.86304291151464" lon="9.344460815191269">
            <ele>931.65</ele>
            <time>2018-04-22T06:14:49Z</time>
        </trkpt>
        <trkpt lat="45.86485574953258" lon="9.345089122653008">
            <ele>962.9</ele>
            <time>2018-04-22T06:20:09Z</time>
        </trkpt>
        <trkpt lat="45.864985501393676" lon="9.344984432682395">
            <ele>976.36</ele>
            <time>2018-04-22T06:21:44Z</time>
        </trkpt>
        <trkpt lat="45.864895060658455" lon="9.344952246174216">
            <ele>978.28</ele>
            <time>2018-04-22T06:22:50Z</time>
        </trkpt>
        <trkpt lat="45.865287417545915" lon="9.34494654648006">
            <ele>1006.64</ele>
            <time>2018-04-22T06:27:04Z</time>
        </trkpt>
        <trkpt lat="45.865415995940566" lon="9.345136564224958">
            <ele>1016.25</ele>
            <time>2018-04-22T06:27:54Z</time>
        </trkpt>
        <trkpt lat="45.86592678911984" lon="9.344976134598255">
            <ele>1059.51</ele>
            <time>2018-04-22T06:31:36Z</time>
        </trkpt>
        <trkpt lat="45.86606274358928" lon="9.345327336341143">
            <ele>1080.66</ele>
            <time>2018-04-22T06:33:29Z</time>
        </trkpt>
        <trkpt lat="45.86623557843268" lon="9.345093732699752">
            <ele>1094.6</ele>
            <time>2018-04-22T06:34:36Z</time>
        </trkpt>
        <trkpt lat="45.866154693067074" lon="9.344870774075389">
            <ele>1104.21</ele>
            <time>2018-04-22T06:35:20Z</time>
        </trkpt>
        <trkpt lat="45.86601882241666" lon="9.344946211203933">
            <ele>1109.5</ele>
            <time>2018-04-22T06:36:23Z</time>
        </trkpt>
        <trkpt lat="45.86611848324537" lon="9.345118878409266">
            <ele>1125.36</ele>
            <time>2018-04-22T06:37:52Z</time>
        </trkpt>
        <trkpt lat="45.86636164225638" lon="9.344824757426977">
            <ele>1153.24</ele>
            <time>2018-04-22T06:40:10Z</time>
        </trkpt>
        <trkpt lat="45.86683798581362" lon="9.345006896182895">
            <ele>1172.95</ele>
            <time>2018-04-22T06:41:53Z</time>
        </trkpt>
        <trkpt lat="45.86726663634181" lon="9.344897260889411">
            <ele>1181.6</ele>
            <time>2018-04-22T06:43:44Z</time>
        </trkpt>
        <trkpt lat="45.86687872186303" lon="9.34376997873187">
            <ele>1220.53</ele>
            <time>2018-04-22T06:48:56Z</time>
        </trkpt>
        <trkpt lat="45.866934545338154" lon="9.342484781518579">
            <ele>1242.64</ele>
            <time>2018-04-22T06:51:33Z</time>
        </trkpt>
        <trkpt lat="45.86654051207006" lon="9.341853708028793">
            <ele>1267.64</ele>
            <time>2018-04-22T06:54:09Z</time>
        </trkpt>
        <trkpt lat="45.86614849045873" lon="9.340697256848216">
            <ele>1290.23</ele>
            <time>2018-04-22T06:56:38Z</time>
        </trkpt>
        <trkpt lat="45.86637916043401" lon="9.339670641347766">
            <ele>1273.4</ele>
            <time>2018-04-22T07:18:31Z</time>
        </trkpt>
        <trkpt lat="45.86600013077259" lon="9.339519431814551">
            <ele>1245.04</ele>
            <time>2018-04-22T07:27:16Z</time>
        </trkpt>
        <trkpt lat="45.86599711328745" lon="9.338957089930773">
            <ele>1237.83</ele>
            <time>2018-04-22T07:28:47Z</time>
        </trkpt>
        <trkpt lat="45.86623063310981" lon="9.338617455214262">
            <ele>1264.27</ele>
            <time>2018-04-22T07:31:31Z</time>
        </trkpt>
        <trkpt lat="45.8656420558691" lon="9.337970623746514">
            <ele>1259.94</ele>
            <time>2018-04-22T07:35:41Z</time>
        </trkpt>
        <trkpt lat="45.86525623686612" lon="9.33802611194551">
            <ele>1240.72</ele>
            <time>2018-04-22T07:38:01Z</time>
        </trkpt>
        <trkpt lat="45.864636143669486" lon="9.337062109261751">
            <ele>1225.34</ele>
            <time>2018-04-22T07:41:15Z</time>
        </trkpt>
        <trkpt lat="45.86438267491758" lon="9.336980218067765">
            <ele>1211.4</ele>
            <time>2018-04-22T07:42:15Z</time>
        </trkpt>
        <trkpt lat="45.86436230689287" lon="9.336499013006687">
            <ele>1196.5</ele>
            <time>2018-04-22T07:43:45Z</time>
        </trkpt>
        <trkpt lat="45.86420740932226" lon="9.336567744612694">
            <ele>1184.96</ele>
            <time>2018-04-22T07:44:39Z</time>
        </trkpt>
        <trkpt lat="45.86419500410557" lon="9.335956955328584">
            <ele>1181.12</ele>
            <time>2018-04-22T07:45:54Z</time>
        </trkpt>
        <trkpt lat="45.86350567638874" lon="9.334914665669203">
            <ele>1141.22</ele>
            <time>2018-04-22T07:51:06Z</time>
        </trkpt>
        <trkpt lat="45.86348472163081" lon="9.333724519237876">
            <ele>1119.11</ele>
            <time>2018-04-22T07:55:16Z</time>
        </trkpt>
        <trkpt lat="45.863053891807795" lon="9.332624645903707">
            <ele>1142.18</ele>
            <time>2018-04-22T07:58:09Z</time>
        </trkpt>
        <trkpt lat="45.86256489157677" lon="9.33201846666634">
            <ele>1157.08</ele>
            <time>2018-04-22T08:00:05Z</time>
        </trkpt>
        <trkpt lat="45.86249113082886" lon="9.33169199153781">
            <ele>1166.7</ele>
            <time>2018-04-22T08:01:03Z</time>
        </trkpt>
        <trkpt lat="45.86232206784189" lon="9.331701211631298">
            <ele>1172.47</ele>
            <time>2018-04-22T08:01:45Z</time>
        </trkpt>
        <trkpt lat="45.862354254350066" lon="9.331220593303442">
            <ele>1183.04</ele>
            <time>2018-04-22T08:02:55Z</time>
        </trkpt>
        <trkpt lat="45.86218737065792" lon="9.330914570018649">
            <ele>1190.25</ele>
            <time>2018-04-22T08:03:50Z</time>
        </trkpt>
        <trkpt lat="45.862015625461936" lon="9.330779453739524">
            <ele>1197.46</ele>
            <time>2018-04-22T08:04:30Z</time>
        </trkpt>
        <trkpt lat="45.861231749877334" lon="9.331178599968553">
            <ele>1216.21</ele>
            <time>2018-04-22T08:07:11Z</time>
        </trkpt>
        <trkpt lat="45.86109361611307" lon="9.332381235435605">
            <ele>1242.16</ele>
            <time>2018-04-22T08:09:57Z</time>
        </trkpt>
        <trkpt lat="45.86145043373108" lon="9.330067662522197">
            <ele>1238.8</ele>
            <time>2018-04-22T08:21:24Z</time>
        </trkpt>
        <trkpt lat="45.86170440539718" lon="9.32945259846747">
            <ele>1260.91</ele>
            <time>2018-04-22T08:28:12Z</time>
        </trkpt>
        <trkpt lat="45.8619986101985" lon="9.329586457461119">
            <ele>1289.75</ele>
            <time>2018-04-22T08:33:08Z</time>
        </trkpt>
        <trkpt lat="45.86225660517812" lon="9.329018164426088">
            <ele>1324.83</ele>
            <time>2018-04-22T08:36:52Z</time>
        </trkpt>
        <trkpt lat="45.86233355104923" lon="9.328609379008412">
            <ele>1347.43</ele>
            <time>2018-04-22T08:41:34Z</time>
        </trkpt>
        <trkpt lat="45.86221184581518" lon="9.327964391559362">
            <ele>1366.65</ele>
            <time>2018-04-22T08:43:55Z</time>
        </trkpt>
        <trkpt lat="45.86241837590933" lon="9.3271473236382">
            <ele>1351.75</ele>
            <time>2018-04-22T09:08:31Z</time>
        </trkpt>
        <trkpt lat="45.86268567480147" lon="9.326906008645892">
            <ele>1330.6</ele>
            <time>2018-04-22T09:11:26Z</time>
        </trkpt>
        <trkpt lat="45.8629035204649" lon="9.324433766305447">
            <ele>1304.65</ele>
            <time>2018-04-22T09:16:48Z</time>
        </trkpt>
        <trkpt lat="45.863175513222814" lon="9.323868826031685">
            <ele>1311.38</ele>
            <time>2018-04-22T09:18:43Z</time>
        </trkpt>
        <trkpt lat="45.86284711025655" lon="9.32332869619131">
            <ele>1360.88</ele>
            <time>2018-04-22T09:25:07Z</time>
        </trkpt>
        <trkpt lat="45.86267603561282" lon="9.323389632627368">
            <ele>1369.05</ele>
            <time>2018-04-22T09:26:18Z</time>
        </trkpt>
        <trkpt lat="45.8625269215554" lon="9.323164913803339">
            <ele>1378.67</ele>
            <time>2018-04-22T09:27:44Z</time>
        </trkpt>
        <trkpt lat="45.86245056241751" lon="9.321905029937625">
            <ele>1359.92</ele>
            <time>2018-04-22T09:52:22Z</time>
        </trkpt>
        <trkpt lat="45.86226029321551" lon="9.32164535857737">
            <ele>1344.06</ele>
            <time>2018-04-22T09:55:00Z</time>
        </trkpt>
        <trkpt lat="45.86217890493572" lon="9.320788811892271">
            <ele>1326.76</ele>
            <time>2018-04-22T09:58:34Z</time>
        </trkpt>
        <trkpt lat="45.8622142765671" lon="9.32061136700213">
            <ele>1318.59</ele>
            <time>2018-04-22T10:00:34Z</time>
        </trkpt>
        <trkpt lat="45.862725991755724" lon="9.321050243452191">
            <ele>1286.86</ele>
            <time>2018-04-22T10:04:17Z</time>
        </trkpt>
        <trkpt lat="45.86267368867993" lon="9.320735922083259">
            <ele>1271.96</ele>
            <time>2018-04-22T10:05:14Z</time>
        </trkpt>
        <trkpt lat="45.862845266237855" lon="9.320626873522997">
            <ele>1264.75</ele>
            <time>2018-04-22T10:05:52Z</time>
        </trkpt>
        <trkpt lat="45.86290016770363" lon="9.320199312642217">
            <ele>1250.81</ele>
            <time>2018-04-22T10:09:01Z</time>
        </trkpt>
        <trkpt lat="45.86281081661582" lon="9.319582153111696">
            <ele>1240.24</ele>
            <time>2018-04-22T10:10:10Z</time>
        </trkpt>
        <trkpt lat="45.86258358322084" lon="9.319418873637915">
            <ele>1231.59</ele>
            <time>2018-04-22T10:11:37Z</time>
        </trkpt>
        <trkpt lat="45.86240714415908" lon="9.31969522498548">
            <ele>1216.69</ele>
            <time>2018-04-22T10:14:31Z</time>
        </trkpt>
        <trkpt lat="45.86202593520284" lon="9.31920999661088">
            <ele>1186.4</ele>
            <time>2018-04-22T10:16:56Z</time>
        </trkpt>
        <trkpt lat="45.86169920861721" lon="9.319239249452949">
            <ele>1170.54</ele>
            <time>2018-04-22T10:18:26Z</time>
        </trkpt>
        <trkpt lat="45.86165813729167" lon="9.318340122699738">
            <ele>1142.66</ele>
            <time>2018-04-22T10:20:30Z</time>
        </trkpt>
        <trkpt lat="45.86135705932975" lon="9.317954806610942">
            <ele>1124.88</ele>
            <time>2018-04-22T10:21:56Z</time>
        </trkpt>
        <trkpt lat="45.860790107399225" lon="9.318033512681723">
            <ele>1092.68</ele>
            <time>2018-04-22T10:24:31Z</time>
        </trkpt>
        <trkpt lat="45.86037562228739" lon="9.318334506824613">
            <ele>1070.57</ele>
            <time>2018-04-22T10:26:12Z</time>
        </trkpt>
        <trkpt lat="45.86042742244899" lon="9.317611651495099">
            <ele>1055.18</ele>
            <time>2018-04-22T10:27:39Z</time>
        </trkpt>
        <trkpt lat="45.860266322270036" lon="9.317060122266412">
            <ele>1041.73</ele>
            <time>2018-04-22T10:28:44Z</time>
        </trkpt>
        <trkpt lat="45.8599038887769" lon="9.317176882177591">
            <ele>1022.5</ele>
            <time>2018-04-22T10:30:17Z</time>
        </trkpt>
        <trkpt lat="45.8600143622607" lon="9.317462621256709">
            <ele>1024.42</ele>
            <time>2018-04-22T10:30:44Z</time>
        </trkpt>
        <trkpt lat="45.85988159291446" lon="9.31825965642929">
            <ele>1036.44</ele>
            <time>2018-04-22T10:32:10Z</time>
        </trkpt>
        <trkpt lat="45.859970189630985" lon="9.319349136203527">
            <ele>1041.73</ele>
            <time>2018-04-22T10:33:38Z</time>
        </trkpt>
        <trkpt lat="45.859717056155205" lon="9.321742672473192">
            <ele>1040.76</ele>
            <time>2018-04-22T10:36:38Z</time>
        </trkpt>
        <trkpt lat="45.85911909118295" lon="9.323902018368244">
            <ele>1032.59</ele>
            <time>2018-04-22T10:39:17Z</time>
        </trkpt>
        <trkpt lat="45.858775014057755" lon="9.324485566467047">
            <ele>1027.79</ele>
            <time>2018-04-22T10:40:11Z</time>
        </trkpt>
        <trkpt lat="45.858181742951274" lon="9.324993677437305">
            <ele>1022.98</ele>
            <time>2018-04-22T10:41:15Z</time>
        </trkpt>
        <trkpt lat="45.85783959366381" lon="9.325900599360466">
            <ele>1023.46</ele>
            <time>2018-04-22T10:43:06Z</time>
        </trkpt>
        <trkpt lat="45.857252357527614" lon="9.326136382296681">
            <ele>1018.65</ele>
            <time>2018-04-22T10:44:26Z</time>
        </trkpt>
        <trkpt lat="45.8578176330775" lon="9.328661598265171">
            <ele>1019.13</ele>
            <time>2018-04-22T10:49:20Z</time>
        </trkpt>
        <trkpt lat="45.85724246688187" lon="9.326182818040252">
            <ele>1021.06</ele>
            <time>2018-04-22T10:55:45Z</time>
        </trkpt>
        <trkpt lat="45.85707566700876" lon="9.326195223256946">
            <ele>1020.1</ele>
            <time>2018-04-22T10:56:26Z</time>
        </trkpt>
        <trkpt lat="45.85684172809124" lon="9.325779899954796">
            <ele>1026.83</ele>
            <time>2018-04-22T10:57:28Z</time>
        </trkpt>
        <trkpt lat="45.855142548680305" lon="9.325131140649319">
            <ele>1086.43</ele>
            <time>2018-04-22T11:03:53Z</time>
        </trkpt>
        <trkpt lat="45.854417346417904" lon="9.32459469884634">
            <ele>1118.15</ele>
            <time>2018-04-22T11:07:08Z</time>
        </trkpt>
        <trkpt lat="45.854272758588195" lon="9.324667118489742">
            <ele>1123.92</ele>
            <time>2018-04-22T11:07:41Z</time>
        </trkpt>
        <trkpt lat="45.85424702614546" lon="9.324372243136168">
            <ele>1129.21</ele>
            <time>2018-04-22T11:08:49Z</time>
        </trkpt>
        <trkpt lat="45.85378836840391" lon="9.32419060729444">
            <ele>1155.64</ele>
            <time>2018-04-22T11:12:13Z</time>
        </trkpt>
        <trkpt lat="45.85278958082199" lon="9.321960853412747">
            <ele>1160.93</ele>
            <time>2018-04-22T11:18:08Z</time>
        </trkpt>
        <trkpt lat="45.85257005877793" lon="9.3219546508044">
            <ele>1158.53</ele>
            <time>2018-04-22T11:18:51Z</time>
        </trkpt>
        <trkpt lat="45.85247727110982" lon="9.321551732718945">
            <ele>1165.26</ele>
            <time>2018-04-22T11:19:38Z</time>
        </trkpt>
        <trkpt lat="45.85053652524948" lon="9.318443136289716">
            <ele>1204.67</ele>
            <time>2018-04-22T11:25:48Z</time>
        </trkpt>
        <trkpt lat="45.85038707591593" lon="9.318378511816263">
            <ele>1208.03</ele>
            <time>2018-04-22T11:26:13Z</time>
        </trkpt>
        <trkpt lat="45.85030518472195" lon="9.318635249510407">
            <ele>1211.4</ele>
            <time>2018-04-22T11:27:54Z</time>
        </trkpt>
        <trkpt lat="45.849435813724995" lon="9.318654611706734">
            <ele>1239.28</ele>
            <time>2018-04-22T11:30:38Z</time>
        </trkpt>
        <trkpt lat="45.84790410473943" lon="9.317841567099094">
            <ele>1244.56</ele>
            <time>2018-04-22T11:34:39Z</time>
        </trkpt>
        <trkpt lat="45.846785958856344" lon="9.317750204354525">
            <ele>1206.11</ele>
            <time>2018-04-22T11:38:29Z</time>
        </trkpt>
        <trkpt lat="45.84621992893517" lon="9.31793862953782">
            <ele>1197.94</ele>
            <time>2018-04-22T11:39:32Z</time>
        </trkpt>
        <trkpt lat="45.84550461731851" lon="9.318537348881364">
            <ele>1190.73</ele>
            <time>2018-04-22T11:42:00Z</time>
        </trkpt>
        <trkpt lat="45.845365058630705" lon="9.317883308976889">
            <ele>1181.12</ele>
            <time>2018-04-22T11:45:11Z</time>
        </trkpt>
        <trkpt lat="45.84490539506078" lon="9.317629924044013">
            <ele>1179.19</ele>
            <time>2018-04-22T11:45:39Z</time>
        </trkpt>
        <trkpt lat="45.844382951036096" lon="9.317858582362533">
            <ele>1177.27</ele>
            <time>2018-04-22T11:46:31Z</time>
        </trkpt>
        <trkpt lat="45.843984140083194" lon="9.31756873615086">
            <ele>1172.95</ele>
            <time>2018-04-22T11:47:10Z</time>
        </trkpt>
        <trkpt lat="45.843531265854836" lon="9.316775975748897">
            <ele>1162.37</ele>
            <time>2018-04-22T11:48:19Z</time>
        </trkpt>
        <trkpt lat="45.842848140746355" lon="9.313404522836208">
            <ele>1132.57</ele>
            <time>2018-04-22T11:51:59Z</time>
        </trkpt>
        <trkpt lat="45.841723373159766" lon="9.311667289584875">
            <ele>1119.11</ele>
            <time>2018-04-22T11:54:04Z</time>
        </trkpt>
        <trkpt lat="45.840620482340455" lon="9.307761322706938">
            <ele>1119.59</ele>
            <time>2018-04-22T11:58:23Z</time>
        </trkpt>
        <trkpt lat="45.839492697268724" lon="9.30616507306695">
            <ele>1120.55</ele>
            <time>2018-04-22T12:00:34Z</time>
        </trkpt>
        <trkpt lat="45.83938213996589" lon="9.305057739838958">
            <ele>1128.73</ele>
            <time>2018-04-22T12:02:06Z</time>
        </trkpt>
        <trkpt lat="45.83853372372687" lon="9.30293275974691">
            <ele>1180.64</ele>
            <time>2018-04-22T12:07:07Z</time>
        </trkpt>
        <trkpt lat="45.83857865072787" lon="9.302653642371297">
            <ele>1188.81</ele>
            <time>2018-04-22T12:08:02Z</time>
        </trkpt>
        <trkpt lat="45.837110225111246" lon="9.30199415422976">
            <ele>1242.16</ele>
            <time>2018-04-22T13:19:25Z</time>
        </trkpt>
        <trkpt lat="45.8367205504328" lon="9.302236307412386">
            <ele>1222.45</ele>
            <time>2018-04-22T13:21:59Z</time>
        </trkpt>
        <trkpt lat="45.836924985051155" lon="9.302722960710526">
            <ele>1208.03</ele>
            <time>2018-04-22T13:23:08Z</time>
        </trkpt>
        <trkpt lat="45.837952606379986" lon="9.303141385316849">
            <ele>1174.87</ele>
            <time>2018-04-22T13:25:39Z</time>
        </trkpt>
        <trkpt lat="45.838812086731195" lon="9.304020395502448">
            <ele>1153.24</ele>
            <time>2018-04-22T13:27:32Z</time>
        </trkpt>
        <trkpt lat="45.83959864452481" lon="9.306423487141728">
            <ele>1112.86</ele>
            <time>2018-04-22T13:48:51Z</time>
        </trkpt>
        <trkpt lat="45.840480253100395" lon="9.30787238292396">
            <ele>1114.79</ele>
            <time>2018-04-22T13:50:51Z</time>
        </trkpt>
        <trkpt lat="45.84041747264564" lon="9.308477388694882">
            <ele>1123.92</ele>
            <time>2018-04-22T13:51:52Z</time>
        </trkpt>
        <trkpt lat="45.84138021804392" lon="9.310532547533512">
            <ele>1104.69</ele>
            <time>2018-04-22T13:54:51Z</time>
        </trkpt>
        <trkpt lat="45.84157006815076" lon="9.311618506908417">
            <ele>1109.02</ele>
            <time>2018-04-22T13:56:01Z</time>
        </trkpt>
        <trkpt lat="45.84199419245124" lon="9.312768084928393">
            <ele>1121.52</ele>
            <time>2018-04-22T13:57:40Z</time>
        </trkpt>
        <trkpt lat="45.842159148305655" lon="9.314823662862182">
            <ele>1161.89</ele>
            <time>2018-04-22T14:01:49Z</time>
        </trkpt>
        <trkpt lat="45.84199385717511" lon="9.31577400304377">
            <ele>1179.19</ele>
            <time>2018-04-22T14:03:31Z</time>
        </trkpt>
        <trkpt lat="45.84221564233303" lon="9.317987663671374">
            <ele>1208.03</ele>
            <time>2018-04-22T14:06:50Z</time>
        </trkpt>
        <trkpt lat="45.84339874796569" lon="9.320833068341017">
            <ele>1252.74</ele>
            <time>2018-04-22T14:11:54Z</time>
        </trkpt>
        <trkpt lat="45.84361248649657" lon="9.321959260851145">
            <ele>1250.33</ele>
            <time>2018-04-22T14:16:29Z</time>
        </trkpt>
        <trkpt lat="45.84409637376666" lon="9.322638949379325">
            <ele>1222.45</ele>
            <time>2018-04-22T14:18:25Z</time>
        </trkpt>
        <trkpt lat="45.844329139217734" lon="9.323435481637716">
            <ele>1215.24</ele>
            <time>2018-04-22T14:19:21Z</time>
        </trkpt>
        <trkpt lat="45.84435881115496" lon="9.325229544192553">
            <ele>1202.75</ele>
            <time>2018-04-22T14:22:18Z</time>
        </trkpt>
        <trkpt lat="45.84387140348554" lon="9.325193921104074">
            <ele>1181.6</ele>
            <time>2018-04-22T14:24:44Z</time>
        </trkpt>
        <trkpt lat="45.843621706590056" lon="9.326017862185836">
            <ele>1160.45</ele>
            <time>2018-04-22T14:27:05Z</time>
        </trkpt>
        <trkpt lat="45.843428084626794" lon="9.325922392308712">
            <ele>1150.35</ele>
            <time>2018-04-22T14:27:50Z</time>
        </trkpt>
        <trkpt lat="45.84250674583018" lon="9.329314716160297">
            <ele>1116.71</ele>
            <time>2018-04-22T15:09:48Z</time>
        </trkpt>
        <trkpt lat="45.84314259700477" lon="9.327386794611812">
            <ele>1105.65</ele>
            <time>2018-04-22T15:13:55Z</time>
        </trkpt>
        <trkpt lat="45.84325457923114" lon="9.326396891847253">
            <ele>1128.73</ele>
            <time>2018-04-22T15:16:37Z</time>
        </trkpt>
        <trkpt lat="45.84343001246452" lon="9.325913591310382">
            <ele>1149.39</ele>
            <time>2018-04-22T15:18:52Z</time>
        </trkpt>
        <trkpt lat="45.843657832592726" lon="9.326022388413548">
            <ele>1159.49</ele>
            <time>2018-04-22T15:19:59Z</time>
        </trkpt>
        <trkpt lat="45.84378615953028" lon="9.32522694580257">
            <ele>1178.71</ele>
            <time>2018-04-22T15:22:20Z</time>
        </trkpt>
        <trkpt lat="45.84446635097265" lon="9.325346471741796">
            <ele>1191.21</ele>
            <time>2018-04-22T15:27:51Z</time>
        </trkpt>
        <trkpt lat="45.844723004847765" lon="9.325168607756495">
            <ele>1175.35</ele>
            <time>2018-04-22T15:28:56Z</time>
        </trkpt>
        <trkpt lat="45.84538400173187" lon="9.325764309614897">
            <ele>1144.59</ele>
            <time>2018-04-22T15:31:18Z</time>
        </trkpt>
        <trkpt lat="45.84580502472818" lon="9.324601655825973">
            <ele>1128.24</ele>
            <time>2018-04-22T15:33:57Z</time>
        </trkpt>
        <trkpt lat="45.84612186066806" lon="9.324310217052698">
            <ele>1124.4</ele>
            <time>2018-04-22T15:34:43Z</time>
        </trkpt>
        <trkpt lat="45.84644481539726" lon="9.32183981873095">
            <ele>1102.29</ele>
            <time>2018-04-22T15:38:35Z</time>
        </trkpt>
        <trkpt lat="45.84686215035617" lon="9.321226850152016">
            <ele>1094.6</ele>
            <time>2018-04-22T15:51:37Z</time>
        </trkpt>
        <trkpt lat="45.84690364077687" lon="9.321459867060184">
            <ele>1089.31</ele>
            <time>2018-04-22T15:52:05Z</time>
        </trkpt>
        <trkpt lat="45.84703339263797" lon="9.321450144052505">
            <ele>1088.83</ele>
            <time>2018-04-22T15:53:07Z</time>
        </trkpt>
        <trkpt lat="45.8468624856323" lon="9.322542138397694">
            <ele>1077.78</ele>
            <time>2018-04-22T15:55:59Z</time>
        </trkpt>
        <trkpt lat="45.84724101237953" lon="9.323904700577259">
            <ele>1063.84</ele>
            <time>2018-04-22T15:57:33Z</time>
        </trkpt>
        <trkpt lat="45.84757151082158" lon="9.323582584038377">
            <ele>1053.26</ele>
            <time>2018-04-22T15:58:27Z</time>
        </trkpt>
        <trkpt lat="45.847844844684005" lon="9.322447255253792">
            <ele>1023.94</ele>
            <time>2018-04-22T16:00:55Z</time>
        </trkpt>
        <trkpt lat="45.84820861928165" lon="9.322197139263153">
            <ele>1009.52</ele>
            <time>2018-04-22T16:02:13Z</time>
        </trkpt>
        <trkpt lat="45.848263185471296" lon="9.322582203894854">
            <ele>999.91</ele>
            <time>2018-04-22T16:03:05Z</time>
        </trkpt>
        <trkpt lat="45.848809434100986" lon="9.322680607438087">
            <ele>977.8</ele>
            <time>2018-04-22T16:05:04Z</time>
        </trkpt>
        <trkpt lat="45.84912920370698" lon="9.323338083922863">
            <ele>955.69</ele>
            <time>2018-04-22T16:06:41Z</time>
        </trkpt>
        <trkpt lat="45.84970931522548" lon="9.323894390836358">
            <ele>930.21</ele>
            <time>2018-04-22T16:08:28Z</time>
        </trkpt>
        <trkpt lat="45.84959632717073" lon="9.324192870408297">
            <ele>916.75</ele>
            <time>2018-04-22T16:09:25Z</time>
        </trkpt>
        <trkpt lat="45.849850634112954" lon="9.324581287801266">
            <ele>901.85</ele>
            <time>2018-04-22T16:10:34Z</time>
        </trkpt>
        <trkpt lat="45.84993336349726" lon="9.325267430394888">
            <ele>882.15</ele>
            <time>2018-04-22T16:11:56Z</time>
        </trkpt>
        <trkpt lat="45.85012354888022" lon="9.325416712090373">
            <ele>877.34</ele>
            <time>2018-04-22T16:12:23Z</time>
        </trkpt>
        <trkpt lat="45.8509240206331" lon="9.327248744666576">
            <ele>859.08</ele>
            <time>2018-04-22T16:14:44Z</time>
        </trkpt>
        <trkpt lat="45.85137454792857" lon="9.328657491132617">
            <ele>825.91</ele>
            <time>2018-04-22T16:17:05Z</time>
        </trkpt>
        <trkpt lat="45.85155811160803" lon="9.330299589782953">
            <ele>799.47</ele>
            <time>2018-04-22T16:20:14Z</time>
        </trkpt>
        <trkpt lat="45.85118008777499" lon="9.331605825573206">
            <ele>754.29</ele>
            <time>2018-04-22T16:25:35Z</time>
        </trkpt>
        <trkpt lat="45.850909519940615" lon="9.334095921367407">
            <ele>700.94</ele>
            <time>2018-04-22T16:29:30Z</time>
        </trkpt>
        <trkpt lat="45.85063518024981" lon="9.334129029884934">
            <ele>687.96</ele>
            <time>2018-04-22T16:30:33Z</time>
        </trkpt>
        <trkpt lat="45.850519174709916" lon="9.334891699254513">
            <ele>670.66</ele>
            <time>2018-04-22T16:31:54Z</time>
        </trkpt>
        <trkpt lat="45.84971367381513" lon="9.336688360199332">
            <ele>649.99</ele>
            <time>2018-04-22T16:34:27Z</time>
        </trkpt>
        <trkpt lat="45.849528182297945" lon="9.337474247440696">
            <ele>645.66</ele>
            <time>2018-04-22T16:35:17Z</time>
        </trkpt>
        <trkpt lat="45.848924769088626" lon="9.338705632835627">
            <ele>634.13</ele>
            <time>2018-04-22T16:36:52Z</time>
        </trkpt>
        <trkpt lat="45.848439037799835" lon="9.339270992204547">
            <ele>623.55</ele>
            <time>2018-04-22T16:37:50Z</time>
        </trkpt>
        <trkpt lat="45.84827785380185" lon="9.340204652398825">
            <ele>619.71</ele>
            <time>2018-04-22T16:38:40Z</time>
        </trkpt>
        <trkpt lat="45.84902602247894" lon="9.341878183186054">
            <ele>606.73</ele>
            <time>2018-04-22T16:43:17Z</time>
        </trkpt>
        <trkpt lat="45.849236492067575" lon="9.342059399932623">
            <ele>606.25</ele>
            <time>2018-04-22T16:43:38Z</time>
        </trkpt>
        <trkpt lat="45.84905502386391" lon="9.342338517308235">
            <ele>601.44</ele>
            <time>2018-04-22T16:44:10Z</time>
        </trkpt>
        <trkpt lat="45.848642969504" lon="9.342009108513594">
            <ele>595.67</ele>
            <time>2018-04-22T16:54:46Z</time>
        </trkpt>
        <trkpt lat="45.84897430613637" lon="9.34250883758068">
            <ele>595.19</ele>
            <time>2018-04-22T16:56:05Z</time>
        </trkpt>
        <trkpt lat="45.84876383654773" lon="9.343095067888498">
            <ele>596.64</ele>
            <time>2018-04-22T16:56:53Z</time>
        </trkpt>
        <trkpt lat="45.849502785131335" lon="9.342230558395386">
            <ele>589.43</ele>
            <time>2018-04-22T17:15:38Z</time>
        </trkpt>
        <trkpt lat="45.84998684003949" lon="9.34217356145382">
            <ele>577.89</ele>
            <time>2018-04-22T17:16:47Z</time>
        </trkpt>
        <trkpt lat="45.850738529115915" lon="9.342508250847459">
            <ele>555.3</ele>
            <time>2018-04-22T17:18:45Z</time>
        </trkpt>
        <trkpt lat="45.85165693424642" lon="9.342288561165333">
            <ele>546.65</ele>
            <time>2018-04-22T17:20:09Z</time>
        </trkpt>
        <trkpt lat="45.85151553153992" lon="9.342744117602706">
            <ele>544.24</ele>
            <time>2018-04-22T17:20:48Z</time>
        </trkpt>
        <trkpt lat="45.851740669459105" lon="9.34386326931417">
            <ele>529.82</ele>
            <time>2018-04-22T17:22:24Z</time>
        </trkpt>
        <trkpt lat="45.8516357280314" lon="9.345057858154178">
            <ele>512.52</ele>
            <time>2018-04-22T17:23:49Z</time>
        </trkpt>
        <trkpt lat="45.851864805445075" lon="9.345326498150826">
            <ele>508.67</ele>
            <time>2018-04-22T17:24:12Z</time>
        </trkpt>
        <trkpt lat="45.85230099968612" lon="9.345431188121438">
            <ele>505.79</ele>
            <time>2018-04-22T17:24:34Z</time>
        </trkpt>
        <trkpt lat="45.85263518616557" lon="9.34620140120387">
            <ele>496.18</ele>
            <time>2018-04-22T17:25:35Z</time>
        </trkpt>
        <trkpt lat="45.85265479981899" lon="9.34663524851203">
            <ele>488.49</ele>
            <time>2018-04-22T17:26:09Z</time>
        </trkpt>
        <trkpt lat="45.85247031413019" lon="9.34694018214941">
            <ele>481.28</ele>
            <time>2018-04-22T17:26:48Z</time>
        </trkpt>
        <trkpt lat="45.85191442631185" lon="9.347133552655578">
            <ele>467.82</ele>
            <time>2018-04-22T17:27:58Z</time>
        </trkpt>
        <trkpt lat="45.85163145326078" lon="9.34703690931201">
            <ele>465.42</ele>
            <time>2018-04-22T17:28:20Z</time>
        </trkpt>
        <trkpt lat="45.85143749602139" lon="9.346210788935423">
            <ele>455.8</ele>
            <time>2018-04-22T17:29:24Z</time>
        </trkpt>
        <trkpt lat="45.85113541223109" lon="9.347523478791118">
            <ele>443.79</ele>
            <time>2018-04-22T17:30:59Z</time>
        </trkpt>
        <trkpt lat="45.85167596116662" lon="9.348974721506238">
            <ele>424.08</ele>
            <time>2018-04-22T17:33:05Z</time>
        </trkpt>
        <trkpt lat="45.85223897360265" lon="9.349160799756646">
            <ele>419.27</ele>
            <time>2018-04-22T17:33:53Z</time>
        </trkpt>
        <trkpt lat="45.852328492328525" lon="9.349368335679173">
            <ele>418.31</ele>
            <time>2018-04-22T17:34:11Z</time>
        </trkpt>
        <trkpt lat="45.85225431248546" lon="9.350253380835056">
            <ele>409.18</ele>
            <time>2018-04-22T17:35:12Z</time>
        </trkpt>
        <trkpt lat="45.852361181750894" lon="9.350401069968939">
            <ele>407.74</ele>
            <time>2018-04-22T17:35:59Z</time>
        </trkpt>
        <trkpt lat="45.85216697305441" lon="9.350671973079443">
            <ele>401.97</ele>
            <time>2018-04-22T17:36:36Z</time>
        </trkpt>
        <trkpt lat="45.851667914539576" lon="9.350758893415332">
            <ele>391.87</ele>
            <time>2018-04-22T17:37:22Z</time>
        </trkpt>
        <trkpt lat="45.851630698889494" lon="9.351206487044692">
            <ele>385.15</ele>
            <time>2018-04-22T17:37:57Z</time>
        </trkpt>
        <trkpt lat="45.8507273811847" lon="9.350197557359934">
            <ele>361.11</ele>
            <time>2018-04-22T17:40:06Z</time>
        </trkpt>
        <trkpt lat="45.85061816498637" lon="9.35083843767643">
            <ele>351.02</ele>
            <time>2018-04-22T17:40:53Z</time>
        </trkpt>
        <trkpt lat="45.85025053471327" lon="9.351462051272392">
            <ele>338.04</ele>
            <time>2018-04-22T17:42:33Z</time>
        </trkpt>
    </trkseg>
</trk>
