<?xml version="1.0" encoding="UTF-8" standalone="yes"?>
<trk>
    <name>4 Burgwies - Botanischer Garten</name>
    <trkseg>
        <trkpt lat="47.35801334492862" lon="8.57263907790184">
            <ele>449.42</ele>
            <time>2018-02-09T10:31:46Z</time>
        </trkpt>
        <trkpt lat="47.35815147869289" lon="8.572083776816726">
            <ele>447.09</ele>
            <time>2018-02-09T10:32:22Z</time>
        </trkpt>
        <trkpt lat="47.35800001770258" lon="8.570034317672253">
            <ele>441.83</ele>
            <time>2018-02-09T10:34:16Z</time>
        </trkpt>
        <trkpt lat="47.358627235516906" lon="8.569507850334048">
            <ele>438.94</ele>
            <time>2018-02-09T10:35:26Z</time>
        </trkpt>
        <trkpt lat="47.358852960169315" lon="8.568514762446284">
            <ele>435.33</ele>
            <time>2018-02-09T10:36:33Z</time>
        </trkpt>
        <trkpt lat="47.35867819748819" lon="8.56702420860529">
            <ele>434.85</ele>
            <time>2018-02-09T10:38:10Z</time>
        </trkpt>
        <trkpt lat="47.359232576563954" lon="8.566225748509169">
            <ele>435.04</ele>
            <time>2018-02-09T10:39:15Z</time>
        </trkpt>
        <trkpt lat="47.359619652852416" lon="8.566026343032718">
            <ele>432.65</ele>
            <time>2018-02-09T10:39:56Z</time>
        </trkpt>
        <trkpt lat="47.35963105224073" lon="8.565029567107558">
            <ele>429.65</ele>
            <time>2018-02-09T10:41:02Z</time>
        </trkpt>
        <trkpt lat="47.35944296233356" lon="8.565179267898202">
            <ele>429.88</ele>
            <time>2018-02-09T10:41:32Z</time>
        </trkpt>
        <trkpt lat="47.35963490791619" lon="8.56478095985949">
            <ele>429.73</ele>
            <time>2018-02-09T10:43:12Z</time>
        </trkpt>
        <trkpt lat="47.35966541804373" lon="8.56301941908896">
            <ele>426.88</ele>
            <time>2018-02-09T10:45:03Z</time>
        </trkpt>
        <trkpt lat="47.36010052263737" lon="8.561751823872328">
            <ele>425.05</ele>
            <time>2018-02-09T10:46:20Z</time>
        </trkpt>
        <trkpt lat="47.35909226350486" lon="8.561428617686033">
            <ele>433.97</ele>
            <time>2018-02-09T10:48:43Z</time>
        </trkpt>
        <trkpt lat="47.35849681310356" lon="8.560169572010636">
            <ele>441.47</ele>
            <time>2018-02-09T10:51:23Z</time>
        </trkpt>
        <trkpt lat="47.35857618972659" lon="8.559853741899133">
            <ele>441.2</ele>
            <time>2018-02-09T10:51:44Z</time>
        </trkpt>
        <trkpt lat="47.358808955177665" lon="8.55969037860632">
            <ele>441.66</ele>
            <time>2018-02-09T10:52:04Z</time>
        </trkpt>
    </trkseg>
</trk>
