<?xml version="1.0" encoding="UTF-8" standalone="yes"?>
<trk>
    <name>Monte Colmegnone da Cernobbio 1923</name>
    <trkseg>
        <trkpt lat="45.84285912103951" lon="9.073341870680451">
            <ele>233.26</ele>
            <time>2018-03-03T06:43:16Z</time>
        </trkpt>
        <trkpt lat="45.84402973763645" lon="9.073249585926533">
            <ele>240.47</ele>
            <time>2018-03-03T06:45:55Z</time>
        </trkpt>
        <trkpt lat="45.84403124637902" lon="9.073995323851705">
            <ele>247.2</ele>
            <time>2018-03-03T06:46:49Z</time>
        </trkpt>
        <trkpt lat="45.8449215721339" lon="9.074075873941183">
            <ele>266.42</ele>
            <time>2018-03-03T06:49:01Z</time>
        </trkpt>
        <trkpt lat="45.845245365053415" lon="9.075114224106073">
            <ele>276.52</ele>
            <time>2018-03-03T06:50:18Z</time>
        </trkpt>
        <trkpt lat="45.84548743441701" lon="9.075356293469667">
            <ele>281.32</ele>
            <time>2018-03-03T06:50:47Z</time>
        </trkpt>
        <trkpt lat="45.84594785235822" lon="9.07517222687602">
            <ele>286.61</ele>
            <time>2018-03-03T06:51:27Z</time>
        </trkpt>
        <trkpt lat="45.84645235911012" lon="9.073996664956212">
            <ele>302.47</ele>
            <time>2018-03-03T06:53:08Z</time>
        </trkpt>
        <trkpt lat="45.84689760580659" lon="9.074222557246685">
            <ele>301.03</ele>
            <time>2018-03-03T06:53:54Z</time>
        </trkpt>
        <trkpt lat="45.846968684345484" lon="9.073999095708132">
            <ele>307.28</ele>
            <time>2018-03-03T06:54:23Z</time>
        </trkpt>
        <trkpt lat="45.84755273535848" lon="9.074471583589911">
            <ele>314.01</ele>
            <time>2018-03-03T06:55:28Z</time>
        </trkpt>
        <trkpt lat="45.84849829785526" lon="9.074525311589241">
            <ele>324.58</ele>
            <time>2018-03-03T06:56:57Z</time>
        </trkpt>
        <trkpt lat="45.84862746298313" lon="9.075017748400569">
            <ele>333.71</ele>
            <time>2018-03-03T06:57:53Z</time>
        </trkpt>
        <trkpt lat="45.8484719786793" lon="9.075421672314405">
            <ele>343.33</ele>
            <time>2018-03-03T06:58:58Z</time>
        </trkpt>
        <trkpt lat="45.84858228452504" lon="9.076332617551088">
            <ele>350.06</ele>
            <time>2018-03-03T07:00:16Z</time>
        </trkpt>
        <trkpt lat="45.848957961425185" lon="9.077662155032158">
            <ele>361.11</ele>
            <time>2018-03-03T07:01:53Z</time>
        </trkpt>
        <trkpt lat="45.84860634058714" lon="9.07932361587882">
            <ele>371.69</ele>
            <time>2018-03-03T07:03:32Z</time>
        </trkpt>
        <trkpt lat="45.848735170438886" lon="9.079945385456085">
            <ele>373.13</ele>
            <time>2018-03-03T07:04:20Z</time>
        </trkpt>
        <trkpt lat="45.84870365448296" lon="9.082722645252943">
            <ele>401.49</ele>
            <time>2018-03-03T07:07:40Z</time>
        </trkpt>
        <trkpt lat="45.84909098222852" lon="9.08402225933969">
            <ele>418.79</ele>
            <time>2018-03-03T07:09:18Z</time>
        </trkpt>
        <trkpt lat="45.84957922808826" lon="9.0845104213804">
            <ele>428.4</ele>
            <time>2018-03-03T07:10:21Z</time>
        </trkpt>
        <trkpt lat="45.84982800297439" lon="9.084641514346004">
            <ele>432.73</ele>
            <time>2018-03-03T07:10:48Z</time>
        </trkpt>
        <trkpt lat="45.85018549114466" lon="9.084429536014795">
            <ele>438.5</ele>
            <time>2018-03-03T07:11:22Z</time>
        </trkpt>
        <trkpt lat="45.85069955326617" lon="9.083188595250249">
            <ele>447.15</ele>
            <time>2018-03-03T07:12:52Z</time>
        </trkpt>
        <trkpt lat="45.850701397284865" lon="9.08266388811171">
            <ele>447.15</ele>
            <time>2018-03-03T07:13:35Z</time>
        </trkpt>
        <trkpt lat="45.85104363039136" lon="9.08249574713409">
            <ele>455.8</ele>
            <time>2018-03-03T07:14:22Z</time>
        </trkpt>
        <trkpt lat="45.85100549273193" lon="9.082310423254967">
            <ele>459.17</ele>
            <time>2018-03-03T07:14:43Z</time>
        </trkpt>
        <trkpt lat="45.85242630913854" lon="9.081872049719095">
            <ele>480.8</ele>
            <time>2018-03-03T07:17:15Z</time>
        </trkpt>
        <trkpt lat="45.85274767130613" lon="9.082346549257636">
            <ele>486.56</ele>
            <time>2018-03-03T07:18:13Z</time>
        </trkpt>
        <trkpt lat="45.85297683253884" lon="9.081976404413581">
            <ele>502.91</ele>
            <time>2018-03-03T07:19:45Z</time>
        </trkpt>
        <trkpt lat="45.85338125936687" lon="9.082157285884023">
            <ele>513.0</ele>
            <time>2018-03-03T07:20:51Z</time>
        </trkpt>
        <trkpt lat="45.85401560179889" lon="9.083262355998158">
            <ele>532.71</ele>
            <time>2018-03-03T07:23:14Z</time>
        </trkpt>
        <trkpt lat="45.85464248433709" lon="9.083869960159063">
            <ele>546.65</ele>
            <time>2018-03-03T07:24:56Z</time>
        </trkpt>
        <trkpt lat="45.85411811247468" lon="9.081915216520429">
            <ele>579.33</ele>
            <time>2018-03-03T07:29:22Z</time>
        </trkpt>
        <trkpt lat="45.85435263812542" lon="9.081805916503072">
            <ele>586.54</ele>
            <time>2018-03-03T07:30:09Z</time>
        </trkpt>
        <trkpt lat="45.85526484064758" lon="9.0825573541224">
            <ele>603.85</ele>
            <time>2018-03-03T07:33:33Z</time>
        </trkpt>
        <trkpt lat="45.855730371549726" lon="9.083410715684295">
            <ele>614.9</ele>
            <time>2018-03-03T07:35:08Z</time>
        </trkpt>
        <trkpt lat="45.8571270480752" lon="9.084289390593767">
            <ele>641.82</ele>
            <time>2018-03-03T07:42:07Z</time>
        </trkpt>
        <trkpt lat="45.85793330334127" lon="9.084114460274577">
            <ele>661.04</ele>
            <time>2018-03-03T07:44:25Z</time>
        </trkpt>
        <trkpt lat="45.85842582397163" lon="9.083568127825856">
            <ele>679.79</ele>
            <time>2018-03-03T07:46:53Z</time>
        </trkpt>
        <trkpt lat="45.85860821418464" lon="9.084191154688597">
            <ele>681.71</ele>
            <time>2018-03-03T07:49:34Z</time>
        </trkpt>
        <trkpt lat="45.85894483141601" lon="9.08427195623517">
            <ele>673.54</ele>
            <time>2018-03-03T07:50:14Z</time>
        </trkpt>
        <trkpt lat="45.85914314724505" lon="9.085133699700236">
            <ele>667.29</ele>
            <time>2018-03-03T07:51:44Z</time>
        </trkpt>
        <trkpt lat="45.859417486935854" lon="9.085343163460493">
            <ele>666.33</ele>
            <time>2018-03-03T07:52:17Z</time>
        </trkpt>
        <trkpt lat="45.859495270997286" lon="9.085830235853791">
            <ele>663.93</ele>
            <time>2018-03-03T07:53:15Z</time>
        </trkpt>
        <trkpt lat="45.85986977443099" lon="9.08605545759201">
            <ele>659.6</ele>
            <time>2018-03-03T07:53:49Z</time>
        </trkpt>
        <trkpt lat="45.860994793474674" lon="9.087416008114815">
            <ele>645.66</ele>
            <time>2018-03-03T07:55:48Z</time>
        </trkpt>
        <trkpt lat="45.86118799634278" lon="9.088386632502079">
            <ele>638.45</ele>
            <time>2018-03-03T07:56:47Z</time>
        </trkpt>
        <trkpt lat="45.861113145947456" lon="9.088874962180853">
            <ele>637.01</ele>
            <time>2018-03-03T07:57:01Z</time>
        </trkpt>
        <trkpt lat="45.86136653088033" lon="9.089417355135083">
            <ele>634.13</ele>
            <time>2018-03-03T07:57:36Z</time>
        </trkpt>
        <trkpt lat="45.862190052866936" lon="9.089900655671954">
            <ele>626.44</ele>
            <time>2018-03-03T07:58:46Z</time>
        </trkpt>
        <trkpt lat="45.86267259903252" lon="9.089882634580135">
            <ele>622.11</ele>
            <time>2018-03-03T07:59:58Z</time>
        </trkpt>
        <trkpt lat="45.86250672116876" lon="9.088297951966524">
            <ele>638.45</ele>
            <time>2018-03-03T08:05:54Z</time>
        </trkpt>
        <trkpt lat="45.862825233489275" lon="9.085211651399732">
            <ele>694.69</ele>
            <time>2018-03-03T08:12:13Z</time>
        </trkpt>
        <trkpt lat="45.86364146322012" lon="9.084350746124983">
            <ele>714.4</ele>
            <time>2018-03-03T08:14:54Z</time>
        </trkpt>
        <trkpt lat="45.8642157074064" lon="9.082566406577826">
            <ele>757.18</ele>
            <time>2018-03-03T08:19:28Z</time>
        </trkpt>
        <trkpt lat="45.86496320553124" lon="9.082788778468966">
            <ele>774.0</ele>
            <time>2018-03-03T08:21:14Z</time>
        </trkpt>
        <trkpt lat="45.86506940424442" lon="9.08356192521751">
            <ele>783.61</ele>
            <time>2018-03-03T08:22:15Z</time>
        </trkpt>
        <trkpt lat="45.865128664299846" lon="9.0837247017771">
            <ele>785.53</ele>
            <time>2018-03-03T08:22:32Z</time>
        </trkpt>
        <trkpt lat="45.865355394780636" lon="9.083680361509323">
            <ele>787.94</ele>
            <time>2018-03-03T08:22:49Z</time>
        </trkpt>
        <trkpt lat="45.8656164072454" lon="9.084612345322967">
            <ele>807.16</ele>
            <time>2018-03-03T08:24:52Z</time>
        </trkpt>
        <trkpt lat="45.8661344088614" lon="9.084490220993757">
            <ele>818.22</ele>
            <time>2018-03-03T08:26:05Z</time>
        </trkpt>
        <trkpt lat="45.866713766008615" lon="9.084884421899915">
            <ele>843.69</ele>
            <time>2018-03-03T08:28:33Z</time>
        </trkpt>
        <trkpt lat="45.866844188421965" lon="9.084760705009103">
            <ele>846.58</ele>
            <time>2018-03-03T08:28:48Z</time>
        </trkpt>
        <trkpt lat="45.86655710823834" lon="9.084014296531677">
            <ele>867.73</ele>
            <time>2018-03-03T08:30:51Z</time>
        </trkpt>
        <trkpt lat="45.86650975048542" lon="9.083348605781794">
            <ele>885.51</ele>
            <time>2018-03-03T08:32:28Z</time>
        </trkpt>
        <trkpt lat="45.866958098486066" lon="9.083623196929693">
            <ele>904.26</ele>
            <time>2018-03-03T08:34:14Z</time>
        </trkpt>
        <trkpt lat="45.86772873066366" lon="9.083250788971782">
            <ele>918.68</ele>
            <time>2018-03-03T08:36:20Z</time>
        </trkpt>
        <trkpt lat="45.86813877336681" lon="9.08357709646225">
            <ele>926.37</ele>
            <time>2018-03-03T08:37:08Z</time>
        </trkpt>
        <trkpt lat="45.86865593679249" lon="9.08264435827732">
            <ele>937.42</ele>
            <time>2018-03-03T08:39:01Z</time>
        </trkpt>
        <trkpt lat="45.86931844241917" lon="9.082116214558482">
            <ele>955.21</ele>
            <time>2018-03-03T08:41:05Z</time>
        </trkpt>
        <trkpt lat="45.86964190006256" lon="9.081520177423954">
            <ele>971.07</ele>
            <time>2018-03-03T08:42:47Z</time>
        </trkpt>
        <trkpt lat="45.87112868204713" lon="9.082211768254638">
            <ele>1006.16</ele>
            <time>2018-03-03T08:47:27Z</time>
        </trkpt>
        <trkpt lat="45.871120635420084" lon="9.082629773765802">
            <ele>1012.41</ele>
            <time>2018-03-03T08:48:16Z</time>
        </trkpt>
        <trkpt lat="45.87143998593092" lon="9.083267971873283">
            <ele>1017.69</ele>
            <time>2018-03-03T08:49:27Z</time>
        </trkpt>
        <trkpt lat="45.87193049490452" lon="9.083519512787461">
            <ele>1027.79</ele>
            <time>2018-03-03T08:50:49Z</time>
        </trkpt>
        <trkpt lat="45.8719936106354" lon="9.083773819729686">
            <ele>1031.15</ele>
            <time>2018-03-03T08:51:16Z</time>
        </trkpt>
        <trkpt lat="45.87263507768512" lon="9.08434328623116">
            <ele>1041.25</ele>
            <time>2018-03-03T08:52:51Z</time>
        </trkpt>
        <trkpt lat="45.87312047369778" lon="9.086453849449754">
            <ele>1076.33</ele>
            <time>2018-03-03T08:56:58Z</time>
        </trkpt>
        <trkpt lat="45.873776357620955" lon="9.086496010422707">
            <ele>1093.64</ele>
            <time>2018-03-03T08:58:49Z</time>
        </trkpt>
        <trkpt lat="45.87417231872678" lon="9.086855761706829">
            <ele>1101.81</ele>
            <time>2018-03-03T08:59:54Z</time>
        </trkpt>
        <trkpt lat="45.87450575083494" lon="9.086725506931543">
            <ele>1110.94</ele>
            <time>2018-03-03T09:00:49Z</time>
        </trkpt>
        <trkpt lat="45.87609923444688" lon="9.087106296792626">
            <ele>1124.88</ele>
            <time>2018-03-03T09:17:37Z</time>
        </trkpt>
        <trkpt lat="45.87740815244615" lon="9.086799183860421">
            <ele>1130.17</ele>
            <time>2018-03-03T09:19:40Z</time>
        </trkpt>
        <trkpt lat="45.87842579931021" lon="9.087075283750892">
            <ele>1137.38</ele>
            <time>2018-03-03T09:21:10Z</time>
        </trkpt>
        <trkpt lat="45.87837651371956" lon="9.087588088586926">
            <ele>1136.9</ele>
            <time>2018-03-03T09:21:53Z</time>
        </trkpt>
        <trkpt lat="45.87859737686813" lon="9.088489646092057">
            <ele>1135.45</ele>
            <time>2018-03-03T09:22:46Z</time>
        </trkpt>
        <trkpt lat="45.879299864172935" lon="9.090189831331372">
            <ele>1139.3</ele>
            <time>2018-03-03T09:24:45Z</time>
        </trkpt>
        <trkpt lat="45.87977352552116" lon="9.090753346681595">
            <ele>1146.03</ele>
            <time>2018-03-03T09:25:45Z</time>
        </trkpt>
        <trkpt lat="45.88050342164934" lon="9.090955182909966">
            <ele>1158.05</ele>
            <time>2018-03-03T09:27:04Z</time>
        </trkpt>
        <trkpt lat="45.88074398227036" lon="9.091215105727315">
            <ele>1160.93</ele>
            <time>2018-03-03T09:27:30Z</time>
        </trkpt>
        <trkpt lat="45.88114455342293" lon="9.09277020022273">
            <ele>1161.41</ele>
            <time>2018-03-03T09:29:07Z</time>
        </trkpt>
        <trkpt lat="45.88100248016417" lon="9.093296583741903">
            <ele>1163.81</ele>
            <time>2018-03-03T09:29:39Z</time>
        </trkpt>
        <trkpt lat="45.87967763654888" lon="9.095149235799909">
            <ele>1179.19</ele>
            <time>2018-03-03T09:32:37Z</time>
        </trkpt>
        <trkpt lat="45.87974863126874" lon="9.095809981226921">
            <ele>1177.27</ele>
            <time>2018-03-03T09:33:21Z</time>
        </trkpt>
        <trkpt lat="45.88029504753649" lon="9.09685704857111">
            <ele>1171.98</ele>
            <time>2018-03-03T09:34:37Z</time>
        </trkpt>
        <trkpt lat="45.88096325285733" lon="9.097731448709965">
            <ele>1171.02</ele>
            <time>2018-03-03T09:35:51Z</time>
        </trkpt>
        <trkpt lat="45.882645919919014" lon="9.098771810531616">
            <ele>1165.74</ele>
            <time>2018-03-03T09:38:21Z</time>
        </trkpt>
        <trkpt lat="45.88489553891122" lon="9.101171214133501">
            <ele>1163.33</ele>
            <time>2018-03-03T09:42:06Z</time>
        </trkpt>
        <trkpt lat="45.88598937727511" lon="9.101434489712119">
            <ele>1160.93</ele>
            <time>2018-03-03T09:43:34Z</time>
        </trkpt>
        <trkpt lat="45.88683536276221" lon="9.101165179163218">
            <ele>1165.26</ele>
            <time>2018-03-03T09:44:51Z</time>
        </trkpt>
        <trkpt lat="45.88721472769976" lon="9.101279340684414">
            <ele>1166.7</ele>
            <time>2018-03-03T09:45:25Z</time>
        </trkpt>
        <trkpt lat="45.888670748099685" lon="9.103891309350729">
            <ele>1159.97</ele>
            <time>2018-03-03T09:48:42Z</time>
        </trkpt>
        <trkpt lat="45.89033581316471" lon="9.107417073100805">
            <ele>1185.92</ele>
            <time>2018-03-03T09:53:21Z</time>
        </trkpt>
        <trkpt lat="45.89107149280608" lon="9.108060467988253">
            <ele>1198.42</ele>
            <time>2018-03-03T09:54:59Z</time>
        </trkpt>
        <trkpt lat="45.89205217547715" lon="9.107623351737857">
            <ele>1213.32</ele>
            <time>2018-03-03T09:56:49Z</time>
        </trkpt>
        <trkpt lat="45.89237613603473" lon="9.107750002294779">
            <ele>1218.61</ele>
            <time>2018-03-03T09:57:25Z</time>
        </trkpt>
        <trkpt lat="45.891973385587335" lon="9.107849663123488">
            <ele>1219.57</ele>
            <time>2018-03-03T09:58:01Z</time>
        </trkpt>
        <trkpt lat="45.89131532236934" lon="9.108672346919775">
            <ele>1219.57</ele>
            <time>2018-03-03T09:59:25Z</time>
        </trkpt>
        <trkpt lat="45.892261723056436" lon="9.110628683120012">
            <ele>1256.1</ele>
            <time>2018-03-03T10:03:12Z</time>
        </trkpt>
        <trkpt lat="45.89313117787242" lon="9.111931398510933">
            <ele>1275.33</ele>
            <time>2018-03-03T10:05:33Z</time>
        </trkpt>
        <trkpt lat="45.893388502299786" lon="9.113154904916883">
            <ele>1285.9</ele>
            <time>2018-03-03T10:07:12Z</time>
        </trkpt>
        <trkpt lat="45.89339311234653" lon="9.113642480224371">
            <ele>1287.34</ele>
            <time>2018-03-03T10:07:46Z</time>
        </trkpt>
        <trkpt lat="45.8924067299813" lon="9.116799859330058">
            <ele>1342.62</ele>
            <time>2018-03-03T10:15:13Z</time>
        </trkpt>
        <trkpt lat="45.89239784516394" lon="9.118288652971387">
            <ele>1374.34</ele>
            <time>2018-03-03T10:21:01Z</time>
        </trkpt>
        <trkpt lat="45.89247730560601" lon="9.116586288437247">
            <ele>1335.89</ele>
            <time>2018-03-03T10:24:27Z</time>
        </trkpt>
        <trkpt lat="45.893179876729846" lon="9.114017821848392">
            <ele>1282.54</ele>
            <time>2018-03-03T10:28:03Z</time>
        </trkpt>
        <trkpt lat="45.89375512674451" lon="9.113177955150604">
            <ele>1286.38</ele>
            <time>2018-03-03T10:29:20Z</time>
        </trkpt>
        <trkpt lat="45.89356569573283" lon="9.113038396462798">
            <ele>1293.11</ele>
            <time>2018-03-03T10:30:09Z</time>
        </trkpt>
        <trkpt lat="45.8935312461108" lon="9.112746538594365">
            <ele>1302.24</ele>
            <time>2018-03-03T10:30:57Z</time>
        </trkpt>
        <trkpt lat="45.89382100850344" lon="9.111700225621462">
            <ele>1328.2</ele>
            <time>2018-03-03T10:33:42Z</time>
        </trkpt>
        <trkpt lat="45.893726125359535" lon="9.110993379727006">
            <ele>1339.25</ele>
            <time>2018-03-03T10:35:09Z</time>
        </trkpt>
        <trkpt lat="45.896127792075276" lon="9.10803146660328">
            <ele>1335.41</ele>
            <time>2018-03-03T10:53:38Z</time>
        </trkpt>
        <trkpt lat="45.89636927470565" lon="9.10701859742403">
            <ele>1342.14</ele>
            <time>2018-03-03T10:55:17Z</time>
        </trkpt>
        <trkpt lat="45.89625695720315" lon="9.105861727148294">
            <ele>1308.01</ele>
            <time>2018-03-03T10:57:30Z</time>
        </trkpt>
        <trkpt lat="45.89636215008795" lon="9.103380013257265">
            <ele>1270.04</ele>
            <time>2018-03-03T11:00:32Z</time>
        </trkpt>
        <trkpt lat="45.894870506599545" lon="9.105187319219112">
            <ele>1227.26</ele>
            <time>2018-03-03T11:03:53Z</time>
        </trkpt>
        <trkpt lat="45.89453129097819" lon="9.105751672759652">
            <ele>1221.49</ele>
            <time>2018-03-03T11:04:19Z</time>
        </trkpt>
        <trkpt lat="45.89447965845466" lon="9.106565807014704">
            <ele>1218.61</ele>
            <time>2018-03-03T11:05:08Z</time>
        </trkpt>
        <trkpt lat="45.89353174902499" lon="9.10769484937191">
            <ele>1212.84</ele>
            <time>2018-03-03T11:06:44Z</time>
        </trkpt>
        <trkpt lat="45.89306755922735" lon="9.107870450243354">
            <ele>1213.32</ele>
            <time>2018-03-03T11:07:20Z</time>
        </trkpt>
        <trkpt lat="45.89194790460169" lon="9.107609270140529">
            <ele>1206.59</ele>
            <time>2018-03-03T11:08:57Z</time>
        </trkpt>
        <trkpt lat="45.89117048308253" lon="9.108032556250691">
            <ele>1195.06</ele>
            <time>2018-03-03T11:10:06Z</time>
        </trkpt>
        <trkpt lat="45.89062297716737" lon="9.107986874878407">
            <ele>1192.65</ele>
            <time>2018-03-03T11:11:54Z</time>
        </trkpt>
        <trkpt lat="45.89030337519944" lon="9.10760055296123">
            <ele>1205.15</ele>
            <time>2018-03-03T12:10:13Z</time>
        </trkpt>
        <trkpt lat="45.88890007697046" lon="9.104299759492278">
            <ele>1165.26</ele>
            <time>2018-03-03T12:14:11Z</time>
        </trkpt>
        <trkpt lat="45.887420838698745" lon="9.101532893255353">
            <ele>1163.81</ele>
            <time>2018-03-03T12:17:37Z</time>
        </trkpt>
        <trkpt lat="45.88692789897323" lon="9.101195270195603">
            <ele>1163.81</ele>
            <time>2018-03-03T12:18:14Z</time>
        </trkpt>
        <trkpt lat="45.88551923632622" lon="9.101471621543169">
            <ele>1158.05</ele>
            <time>2018-03-03T12:21:22Z</time>
        </trkpt>
        <trkpt lat="45.88502403348684" lon="9.101258972659707">
            <ele>1159.49</ele>
            <time>2018-03-03T12:22:41Z</time>
        </trkpt>
        <trkpt lat="45.8832407835871" lon="9.099575467407703">
            <ele>1159.01</ele>
            <time>2018-03-03T12:25:32Z</time>
        </trkpt>
        <trkpt lat="45.88275060988963" lon="9.098842972889543">
            <ele>1159.49</ele>
            <time>2018-03-03T12:26:31Z</time>
        </trkpt>
        <trkpt lat="45.88087541051209" lon="9.09763304516673">
            <ele>1166.22</ele>
            <time>2018-03-03T12:29:24Z</time>
        </trkpt>
        <trkpt lat="45.88016889989376" lon="9.096606932580471">
            <ele>1167.18</ele>
            <time>2018-03-03T12:30:45Z</time>
        </trkpt>
        <trkpt lat="45.879710325971246" lon="9.095462718978524">
            <ele>1171.98</ele>
            <time>2018-03-03T12:32:04Z</time>
        </trkpt>
        <trkpt lat="45.87971158325672" lon="9.094695188105106">
            <ele>1166.7</ele>
            <time>2018-03-03T12:33:04Z</time>
        </trkpt>
        <trkpt lat="45.880886893719435" lon="9.093343941494823">
            <ele>1154.68</ele>
            <time>2018-03-03T12:35:05Z</time>
        </trkpt>
        <trkpt lat="45.88111731223762" lon="9.092615218833089">
            <ele>1151.8</ele>
            <time>2018-03-03T12:35:46Z</time>
        </trkpt>
        <trkpt lat="45.88053183630109" lon="9.091025842353702">
            <ele>1148.91</ele>
            <time>2018-03-03T12:37:29Z</time>
        </trkpt>
        <trkpt lat="45.87963287718594" lon="9.090695260092616">
            <ele>1133.05</ele>
            <time>2018-03-03T12:39:22Z</time>
        </trkpt>
        <trkpt lat="45.879147816449404" lon="9.090059157460928">
            <ele>1125.84</ele>
            <time>2018-03-03T12:40:21Z</time>
        </trkpt>
        <trkpt lat="45.878525376319885" lon="9.088295605033636">
            <ele>1122.48</ele>
            <time>2018-03-03T12:42:05Z</time>
        </trkpt>
        <trkpt lat="45.87833200581372" lon="9.086991967633367">
            <ele>1121.52</ele>
            <time>2018-03-03T12:43:22Z</time>
        </trkpt>
        <trkpt lat="45.877462634816766" lon="9.08677076920867">
            <ele>1114.79</ele>
            <time>2018-03-03T12:44:33Z</time>
        </trkpt>
        <trkpt lat="45.87641707621515" lon="9.087164215743542">
            <ele>1114.31</ele>
            <time>2018-03-03T12:46:06Z</time>
        </trkpt>
        <trkpt lat="45.876335855573416" lon="9.087010910734534">
            <ele>1112.86</ele>
            <time>2018-03-03T12:47:31Z</time>
        </trkpt>
        <trkpt lat="45.874808337539434" lon="9.08681083470583">
            <ele>1107.58</ele>
            <time>2018-03-03T12:49:39Z</time>
        </trkpt>
        <trkpt lat="45.873855482786894" lon="9.083655551075935">
            <ele>1108.54</ele>
            <time>2018-03-03T12:52:52Z</time>
        </trkpt>
        <trkpt lat="45.87412420660257" lon="9.081808514893055">
            <ele>1110.94</ele>
            <time>2018-03-03T12:54:43Z</time>
        </trkpt>
        <trkpt lat="45.87479542940855" lon="9.081047857180238">
            <ele>1107.1</ele>
            <time>2018-03-03T12:55:52Z</time>
        </trkpt>
        <trkpt lat="45.87481118738651" lon="9.080340173095465">
            <ele>1113.34</ele>
            <time>2018-03-03T12:56:38Z</time>
        </trkpt>
        <trkpt lat="45.873816004022956" lon="9.078351818025112">
            <ele>1146.51</ele>
            <time>2018-03-03T13:00:07Z</time>
        </trkpt>
        <trkpt lat="45.873595559969544" lon="9.077518656849861">
            <ele>1160.45</ele>
            <time>2018-03-03T13:01:27Z</time>
        </trkpt>
        <trkpt lat="45.87356312200427" lon="9.075988456606865">
            <ele>1181.6</ele>
            <time>2018-03-03T13:03:32Z</time>
        </trkpt>
        <trkpt lat="45.87332725524902" lon="9.076165650039911">
            <ele>1185.44</ele>
            <time>2018-03-03T13:04:21Z</time>
        </trkpt>
        <trkpt lat="45.87328962050378" lon="9.075965657830238">
            <ele>1184.96</ele>
            <time>2018-03-03T13:04:35Z</time>
        </trkpt>
        <trkpt lat="45.87365984916687" lon="9.075051443651319">
            <ele>1183.52</ele>
            <time>2018-03-03T13:05:43Z</time>
        </trkpt>
        <trkpt lat="45.87401616387069" lon="9.072507787495852">
            <ele>1200.34</ele>
            <time>2018-03-03T13:08:45Z</time>
        </trkpt>
        <trkpt lat="45.8738256432116" lon="9.071802869439125">
            <ele>1195.54</ele>
            <time>2018-03-03T13:10:16Z</time>
        </trkpt>
        <trkpt lat="45.873201778158545" lon="9.07106090337038">
            <ele>1193.13</ele>
            <time>2018-03-03T13:11:37Z</time>
        </trkpt>
        <trkpt lat="45.87296213954687" lon="9.070440139621496">
            <ele>1204.19</ele>
            <time>2018-03-03T13:12:44Z</time>
        </trkpt>
        <trkpt lat="45.87294411845505" lon="9.069574791938066">
            <ele>1213.32</ele>
            <time>2018-03-03T13:13:55Z</time>
        </trkpt>
        <trkpt lat="45.87266684509814" lon="9.068989902734756">
            <ele>1215.24</ele>
            <time>2018-03-03T13:14:53Z</time>
        </trkpt>
        <trkpt lat="45.87261772714555" lon="9.067989941686392">
            <ele>1218.13</ele>
            <time>2018-03-03T13:16:07Z</time>
        </trkpt>
        <trkpt lat="45.872037364169955" lon="9.066804572939873">
            <ele>1237.35</ele>
            <time>2018-03-03T13:18:29Z</time>
        </trkpt>
        <trkpt lat="45.87105257436633" lon="9.066012315452099">
            <ele>1250.33</ele>
            <time>2018-03-03T13:20:43Z</time>
        </trkpt>
        <trkpt lat="45.87221581488848" lon="9.065576875582337">
            <ele>1276.77</ele>
            <time>2018-03-03T13:23:31Z</time>
        </trkpt>
        <trkpt lat="45.87286180816591" lon="9.065667148679495">
            <ele>1295.99</ele>
            <time>2018-03-03T13:25:25Z</time>
        </trkpt>
        <trkpt lat="45.87356454692781" lon="9.06634465791285">
            <ele>1323.39</ele>
            <time>2018-03-03T13:29:34Z</time>
        </trkpt>
        <trkpt lat="45.873417193070054" lon="9.066406767815351">
            <ele>1323.39</ele>
            <time>2018-03-03T13:29:56Z</time>
        </trkpt>
        <trkpt lat="45.873609809204936" lon="9.06674975529313">
            <ele>1322.91</ele>
            <time>2018-03-03T13:30:29Z</time>
        </trkpt>
        <trkpt lat="45.873691784217954" lon="9.066298557445407">
            <ele>1319.07</ele>
            <time>2018-03-03T13:31:36Z</time>
        </trkpt>
        <trkpt lat="45.874139964580536" lon="9.066244410350919">
            <ele>1302.72</ele>
            <time>2018-03-03T13:33:56Z</time>
        </trkpt>
        <trkpt lat="45.8744163159281" lon="9.066478349268436">
            <ele>1295.99</ele>
            <time>2018-03-03T13:34:30Z</time>
        </trkpt>
        <trkpt lat="45.874511785805225" lon="9.066183054819703">
            <ele>1290.23</ele>
            <time>2018-03-03T13:34:59Z</time>
        </trkpt>
        <trkpt lat="45.87608892470598" lon="9.065630435943604">
            <ele>1238.32</ele>
            <time>2018-03-03T13:39:01Z</time>
        </trkpt>
        <trkpt lat="45.87609906680882" lon="9.064454538747668">
            <ele>1200.34</ele>
            <time>2018-03-03T13:41:19Z</time>
        </trkpt>
        <trkpt lat="45.8768220897764" lon="9.062587385997176">
            <ele>1185.44</ele>
            <time>2018-03-03T13:43:29Z</time>
        </trkpt>
        <trkpt lat="45.87687900289893" lon="9.06096825376153">
            <ele>1174.87</ele>
            <time>2018-03-03T13:45:09Z</time>
        </trkpt>
        <trkpt lat="45.87737940251827" lon="9.059349121525884">
            <ele>1161.89</ele>
            <time>2018-03-03T13:46:47Z</time>
        </trkpt>
        <trkpt lat="45.87751988321543" lon="9.058108096942306">
            <ele>1155.16</ele>
            <time>2018-03-03T13:48:04Z</time>
        </trkpt>
        <trkpt lat="45.877047814428806" lon="9.057223051786423">
            <ele>1156.6</ele>
            <time>2018-03-03T13:49:30Z</time>
        </trkpt>
        <trkpt lat="45.87679451331496" lon="9.055736269801855">
            <ele>1150.84</ele>
            <time>2018-03-03T13:50:56Z</time>
        </trkpt>
        <trkpt lat="45.876490166410804" lon="9.055034620687366">
            <ele>1146.03</ele>
            <time>2018-03-03T13:51:47Z</time>
        </trkpt>
        <trkpt lat="45.87483122013509" lon="9.053004020825028">
            <ele>1115.27</ele>
            <time>2018-03-03T13:54:59Z</time>
        </trkpt>
        <trkpt lat="45.87370335124433" lon="9.052123334258795">
            <ele>1113.34</ele>
            <time>2018-03-03T13:56:55Z</time>
        </trkpt>
        <trkpt lat="45.872366689145565" lon="9.051835834980011">
            <ele>1111.9</ele>
            <time>2018-03-03T13:59:02Z</time>
        </trkpt>
        <trkpt lat="45.87120923213661" lon="9.05205468647182">
            <ele>1098.92</ele>
            <time>2018-03-03T14:00:46Z</time>
        </trkpt>
        <trkpt lat="45.86979327723384" lon="9.051026981323957">
            <ele>1078.74</ele>
            <time>2018-03-03T14:03:07Z</time>
        </trkpt>
        <trkpt lat="45.868735229596496" lon="9.050803435966372">
            <ele>1064.32</ele>
            <time>2018-03-03T14:04:44Z</time>
        </trkpt>
        <trkpt lat="45.86742161773145" lon="9.049619659781456">
            <ele>1056.63</ele>
            <time>2018-03-03T14:07:17Z</time>
        </trkpt>
        <trkpt lat="45.8668545819819" lon="9.049658132717013">
            <ele>1036.92</ele>
            <time>2018-03-03T14:08:45Z</time>
        </trkpt>
        <trkpt lat="45.86621512658894" lon="9.04940927401185">
            <ele>1021.54</ele>
            <time>2018-03-03T14:09:47Z</time>
        </trkpt>
        <trkpt lat="45.86357650347054" lon="9.047520076856017">
            <ele>996.06</ele>
            <time>2018-03-03T14:15:05Z</time>
        </trkpt>
        <trkpt lat="45.86120408959687" lon="9.047920731827617">
            <ele>955.21</ele>
            <time>2018-03-03T14:19:17Z</time>
        </trkpt>
        <trkpt lat="45.860320972278714" lon="9.0486123226583">
            <ele>948.96</ele>
            <time>2018-03-03T14:21:00Z</time>
        </trkpt>
        <trkpt lat="45.85922319442034" lon="9.048818601295352">
            <ele>919.16</ele>
            <time>2018-03-03T14:24:02Z</time>
        </trkpt>
        <trkpt lat="45.85712453350425" lon="9.050588607788086">
            <ele>891.76</ele>
            <time>2018-03-03T14:29:26Z</time>
        </trkpt>
        <trkpt lat="45.85456000640988" lon="9.051888221874833">
            <ele>877.34</ele>
            <time>2018-03-03T14:34:40Z</time>
        </trkpt>
        <trkpt lat="45.854207798838615" lon="9.052353585138917">
            <ele>876.86</ele>
            <time>2018-03-03T14:42:10Z</time>
        </trkpt>
        <trkpt lat="45.853061992675066" lon="9.053013240918517">
            <ele>857.15</ele>
            <time>2018-03-03T14:43:59Z</time>
        </trkpt>
        <trkpt lat="45.852384148165584" lon="9.053043331950903">
            <ele>842.73</ele>
            <time>2018-03-03T14:45:08Z</time>
        </trkpt>
        <trkpt lat="45.8521621953696" lon="9.053484806790948">
            <ele>832.16</ele>
            <time>2018-03-03T14:46:00Z</time>
        </trkpt>
        <trkpt lat="45.85159180685878" lon="9.053779346868396">
            <ele>816.3</ele>
            <time>2018-03-03T14:47:16Z</time>
        </trkpt>
        <trkpt lat="45.850945226848125" lon="9.054452581331134">
            <ele>794.67</ele>
            <time>2018-03-03T14:49:36Z</time>
        </trkpt>
        <trkpt lat="45.85058354772627" lon="9.055073177441955">
            <ele>786.02</ele>
            <time>2018-03-03T14:50:45Z</time>
        </trkpt>
        <trkpt lat="45.85046947002411" lon="9.054953567683697">
            <ele>784.09</ele>
            <time>2018-03-03T14:52:13Z</time>
        </trkpt>
        <trkpt lat="45.85017350502312" lon="9.05610591173172">
            <ele>774.96</ele>
            <time>2018-03-03T14:54:39Z</time>
        </trkpt>
        <trkpt lat="45.84996613673866" lon="9.055901393294334">
            <ele>767.75</ele>
            <time>2018-03-03T14:55:27Z</time>
        </trkpt>
        <trkpt lat="45.849815513938665" lon="9.056189227849245">
            <ele>759.58</ele>
            <time>2018-03-03T14:56:04Z</time>
        </trkpt>
        <trkpt lat="45.84991727024317" lon="9.056626511737704">
            <ele>750.93</ele>
            <time>2018-03-03T14:56:55Z</time>
        </trkpt>
        <trkpt lat="45.849594147875905" lon="9.056559707969427">
            <ele>744.2</ele>
            <time>2018-03-03T14:57:33Z</time>
        </trkpt>
        <trkpt lat="45.849690958857536" lon="9.056869503110647">
            <ele>738.91</ele>
            <time>2018-03-03T14:58:01Z</time>
        </trkpt>
        <trkpt lat="45.850246930494905" lon="9.057361939921975">
            <ele>727.37</ele>
            <time>2018-03-03T14:59:00Z</time>
        </trkpt>
        <trkpt lat="45.84909416735172" lon="9.057132862508297">
            <ele>710.55</ele>
            <time>2018-03-03T15:00:50Z</time>
        </trkpt>
        <trkpt lat="45.849316120147705" lon="9.057540809735656">
            <ele>701.9</ele>
            <time>2018-03-03T15:01:36Z</time>
        </trkpt>
        <trkpt lat="45.849044881761074" lon="9.05760845169425">
            <ele>697.09</ele>
            <time>2018-03-03T15:02:06Z</time>
        </trkpt>
        <trkpt lat="45.84928007796407" lon="9.058099715039134">
            <ele>691.33</ele>
            <time>2018-03-03T15:02:44Z</time>
        </trkpt>
        <trkpt lat="45.85017333738506" lon="9.058755179867148">
            <ele>674.98</ele>
            <time>2018-03-03T15:04:21Z</time>
        </trkpt>
        <trkpt lat="45.84829822182655" lon="9.059281563386321">
            <ele>640.86</ele>
            <time>2018-03-03T15:07:21Z</time>
        </trkpt>
        <trkpt lat="45.84898637607694" lon="9.059883803129196">
            <ele>626.92</ele>
            <time>2018-03-03T15:08:35Z</time>
        </trkpt>
        <trkpt lat="45.84948333911598" lon="9.060615794733167">
            <ele>614.9</ele>
            <time>2018-03-03T15:11:09Z</time>
        </trkpt>
        <trkpt lat="45.8487587235868" lon="9.060894744470716">
            <ele>603.85</ele>
            <time>2018-03-03T15:12:17Z</time>
        </trkpt>
        <trkpt lat="45.84783059544861" lon="9.060617806389928">
            <ele>583.66</ele>
            <time>2018-03-03T15:14:01Z</time>
        </trkpt>
        <trkpt lat="45.847528763115406" lon="9.061135137453675">
            <ele>574.04</ele>
            <time>2018-03-03T15:14:45Z</time>
        </trkpt>
        <trkpt lat="45.847412841394544" lon="9.06231832690537">
            <ele>554.82</ele>
            <time>2018-03-03T15:16:19Z</time>
        </trkpt>
        <trkpt lat="45.847071865573525" lon="9.062264766544104">
            <ele>551.93</ele>
            <time>2018-03-03T15:18:25Z</time>
        </trkpt>
        <trkpt lat="45.84681898355484" lon="9.061620365828276">
            <ele>550.01</ele>
            <time>2018-03-03T15:19:30Z</time>
        </trkpt>
        <trkpt lat="45.84635999053717" lon="9.06151257455349">
            <ele>541.36</ele>
            <time>2018-03-03T15:21:43Z</time>
        </trkpt>
        <trkpt lat="45.84621665999293" lon="9.06102349050343">
            <ele>533.19</ele>
            <time>2018-03-03T15:22:40Z</time>
        </trkpt>
        <trkpt lat="45.84602287039161" lon="9.061219710856676">
            <ele>523.09</ele>
            <time>2018-03-03T15:26:07Z</time>
        </trkpt>
        <trkpt lat="45.84597039967775" lon="9.061905853450298">
            <ele>505.79</ele>
            <time>2018-03-03T15:27:27Z</time>
        </trkpt>
        <trkpt lat="45.84537955932319" lon="9.061948098242283">
            <ele>489.93</ele>
            <time>2018-03-03T15:29:34Z</time>
        </trkpt>
        <trkpt lat="45.84614239633083" lon="9.063509898260236">
            <ele>468.3</ele>
            <time>2018-03-03T15:31:26Z</time>
        </trkpt>
        <trkpt lat="45.847115786746144" lon="9.064881764352322">
            <ele>442.82</ele>
            <time>2018-03-03T15:33:25Z</time>
        </trkpt>
        <trkpt lat="45.846804566681385" lon="9.065711740404367">
            <ele>431.77</ele>
            <time>2018-03-03T15:34:08Z</time>
        </trkpt>
        <trkpt lat="45.847114780917764" lon="9.066406432539225">
            <ele>419.27</ele>
            <time>2018-03-03T15:35:25Z</time>
        </trkpt>
        <trkpt lat="45.846716137602925" lon="9.066350441426039">
            <ele>413.5</ele>
            <time>2018-03-03T15:36:01Z</time>
        </trkpt>
        <trkpt lat="45.846071569249034" lon="9.065584922209382">
            <ele>396.68</ele>
            <time>2018-03-03T15:37:27Z</time>
        </trkpt>
        <trkpt lat="45.845742831006646" lon="9.065703190863132">
            <ele>389.47</ele>
            <time>2018-03-03T15:38:01Z</time>
        </trkpt>
        <trkpt lat="45.84362832829356" lon="9.063209909945726">
            <ele>338.04</ele>
            <time>2018-03-03T15:42:05Z</time>
        </trkpt>
        <trkpt lat="45.843480471521616" lon="9.063352150842547">
            <ele>334.68</ele>
            <time>2018-03-03T15:42:31Z</time>
        </trkpt>
        <trkpt lat="45.84353059530258" lon="9.063873924314976">
            <ele>328.91</ele>
            <time>2018-03-03T15:43:30Z</time>
        </trkpt>
        <trkpt lat="45.84287948906422" lon="9.064410366117954">
            <ele>327.47</ele>
            <time>2018-03-03T15:44:28Z</time>
        </trkpt>
        <trkpt lat="45.8422052487731" lon="9.06535659916699">
            <ele>316.89</ele>
            <time>2018-03-03T15:45:45Z</time>
        </trkpt>
        <trkpt lat="45.84235914051533" lon="9.067116966471076">
            <ele>305.36</ele>
            <time>2018-03-03T15:47:28Z</time>
        </trkpt>
        <trkpt lat="45.842112796381116" lon="9.067545868456364">
            <ele>299.59</ele>
            <time>2018-03-03T15:50:09Z</time>
        </trkpt>
        <trkpt lat="45.84221757017076" lon="9.067871337756515">
            <ele>298.15</ele>
            <time>2018-03-03T15:50:33Z</time>
        </trkpt>
        <trkpt lat="45.841967202723026" lon="9.068694775924087">
            <ele>290.94</ele>
            <time>2018-03-03T15:51:23Z</time>
        </trkpt>
        <trkpt lat="45.843935860320926" lon="9.07083517871797">
            <ele>290.46</ele>
            <time>2018-03-03T15:54:38Z</time>
        </trkpt>
        <trkpt lat="45.84445252083242" lon="9.070551199838519">
            <ele>284.21</ele>
            <time>2018-03-03T15:55:25Z</time>
        </trkpt>
        <trkpt lat="45.84421841427684" lon="9.070759322494268">
            <ele>282.77</ele>
            <time>2018-03-03T15:55:50Z</time>
        </trkpt>
        <trkpt lat="45.843686666339636" lon="9.072143593803048">
            <ele>243.83</ele>
            <time>2018-03-03T15:58:56Z</time>
        </trkpt>
        <trkpt lat="45.84374852478504" lon="9.072320954874158">
            <ele>229.89</ele>
            <time>2018-03-03T16:00:05Z</time>
        </trkpt>
        <trkpt lat="45.84306447766721" lon="9.072773661464453">
            <ele>213.07</ele>
            <time>2018-03-03T16:01:18Z</time>
        </trkpt>
        <trkpt lat="45.84313019178808" lon="9.073341870680451">
            <ele>207.78</ele>
            <time>2018-03-03T16:01:50Z</time>
        </trkpt>
        <trkpt lat="45.84285702556372" lon="9.073331812396646">
            <ele>206.34</ele>
            <time>2018-03-03T16:02:12Z</time>
        </trkpt>
    </trkseg>
</trk>
