<?xml version="1.0" encoding="UTF-8" standalone="yes"?>
<trk>
    <name>Percorso 196</name>
    <trkseg>
        <trkpt lat="46.02283098734915" lon="9.791198736056685">
            <ele>1124.59997558594</ele>
            <time>2018-04-25T04:08:38Z</time>
        </trkpt>
        <trkpt lat="46.023059813305736" lon="9.791163448244333">
            <ele>1148.90002441406</ele>
            <time>2018-04-25T04:15:36Z</time>
        </trkpt>
        <trkpt lat="46.023437501862645" lon="9.792293580248952">
            <ele>1151.59997558594</ele>
            <time>2018-04-25T04:15:40Z</time>
        </trkpt>
        <trkpt lat="46.023612935096025" lon="9.792137173935771">
            <ele>1153.5</ele>
            <time>2018-04-25T04:15:47Z</time>
        </trkpt>
        <trkpt lat="46.023693066090345" lon="9.792878134176135">
            <ele>1154.90002441406</ele>
            <time>2018-04-25T04:15:53Z</time>
        </trkpt>
        <trkpt lat="46.02427292615175" lon="9.794202810153365">
            <ele>1162.59997558594</ele>
            <time>2018-04-25T04:17:39Z</time>
        </trkpt>
        <trkpt lat="46.024543745443225" lon="9.795235628262162">
            <ele>1167.69995117188</ele>
            <time>2018-04-25T04:18:17Z</time>
        </trkpt>
        <trkpt lat="46.0248145647347" lon="9.796522166579962">
            <ele>1172.0</ele>
            <time>2018-04-25T04:18:49Z</time>
        </trkpt>
        <trkpt lat="46.02493668906391" lon="9.798810929059982">
            <ele>1200.30004882812</ele>
            <time>2018-04-25T04:20:13Z</time>
        </trkpt>
        <trkpt lat="46.02510835044086" lon="9.798942524939775">
            <ele>1201.90002441406</ele>
            <time>2018-04-25T04:20:27Z</time>
        </trkpt>
        <trkpt lat="46.025413535535336" lon="9.800531398504972">
            <ele>1224.59997558594</ele>
            <time>2018-04-25T04:21:57Z</time>
        </trkpt>
        <trkpt lat="46.02562333457172" lon="9.800827950239182">
            <ele>1228.30004882812</ele>
            <time>2018-04-25T04:22:37Z</time>
        </trkpt>
        <trkpt lat="46.0255965963006" lon="9.801509818062186">
            <ele>1236.30004882812</ele>
            <time>2018-04-25T04:23:09Z</time>
        </trkpt>
        <trkpt lat="46.02579499594867" lon="9.802034357562661">
            <ele>1247.69995117188</ele>
            <time>2018-04-25T04:23:45Z</time>
        </trkpt>
        <trkpt lat="46.025691982358694" lon="9.802813539281487">
            <ele>1254.59997558594</ele>
            <time>2018-04-25T04:24:33Z</time>
        </trkpt>
        <trkpt lat="46.025867499411106" lon="9.80334285646677">
            <ele>1258.40002441406</ele>
            <time>2018-04-25T04:24:55Z</time>
        </trkpt>
        <trkpt lat="46.02582165040076" lon="9.805519133806229">
            <ele>1280.59997558594</ele>
            <time>2018-04-25T04:26:59Z</time>
        </trkpt>
        <trkpt lat="46.02641299366951" lon="9.80620477348566">
            <ele>1287.80004882812</ele>
            <time>2018-04-25T04:27:53Z</time>
        </trkpt>
        <trkpt lat="46.026226077228785" lon="9.808701490983367">
            <ele>1312.19995117188</ele>
            <time>2018-04-25T04:30:31Z</time>
        </trkpt>
        <trkpt lat="46.02581787854433" lon="9.809275651350617">
            <ele>1317.09997558594</ele>
            <time>2018-04-25T04:31:23Z</time>
        </trkpt>
        <trkpt lat="46.025257129222155" lon="9.811376575380564">
            <ele>1343.59997558594</ele>
            <time>2018-04-25T04:33:53Z</time>
        </trkpt>
        <trkpt lat="46.02536014281213" lon="9.81219288893044">
            <ele>1350.40002441406</ele>
            <time>2018-04-25T04:34:43Z</time>
        </trkpt>
        <trkpt lat="46.02553943172097" lon="9.812286347150803">
            <ele>1351.80004882812</ele>
            <time>2018-04-25T04:35:01Z</time>
        </trkpt>
        <trkpt lat="46.025436418130994" lon="9.813130404800177">
            <ele>1356.80004882812</ele>
            <time>2018-04-25T04:35:47Z</time>
        </trkpt>
        <trkpt lat="46.025707237422466" lon="9.813832305371761">
            <ele>1363.69995117188</ele>
            <time>2018-04-25T04:36:41Z</time>
        </trkpt>
        <trkpt lat="46.02532577700913" lon="9.81541438959539">
            <ele>1391.19995117188</ele>
            <time>2018-04-25T04:38:55Z</time>
        </trkpt>
        <trkpt lat="46.025691982358694" lon="9.81523610651493">
            <ele>1396.19995117188</ele>
            <time>2018-04-25T04:39:41Z</time>
        </trkpt>
        <trkpt lat="46.02544404566288" lon="9.81567095965147">
            <ele>1410.19995117188</ele>
            <time>2018-04-25T04:40:33Z</time>
        </trkpt>
        <trkpt lat="46.025138860568404" lon="9.817023295909166">
            <ele>1444.40002441406</ele>
            <time>2018-04-25T04:42:35Z</time>
        </trkpt>
        <trkpt lat="46.025730120018125" lon="9.817994087934494">
            <ele>1458.09997558594</ele>
            <time>2018-04-25T04:43:39Z</time>
        </trkpt>
        <trkpt lat="46.02596280165017" lon="9.819014584645629">
            <ele>1475.40002441406</ele>
            <time>2018-04-25T04:44:38Z</time>
        </trkpt>
        <trkpt lat="46.02590563707054" lon="9.819274926558137">
            <ele>1477.40002441406</ele>
            <time>2018-04-25T04:44:48Z</time>
        </trkpt>
        <trkpt lat="46.026084925979376" lon="9.819329241290689">
            <ele>1479.40002441406</ele>
            <time>2018-04-25T04:44:58Z</time>
        </trkpt>
        <trkpt lat="46.026065815240145" lon="9.819621099159122">
            <ele>1483.40002441406</ele>
            <time>2018-04-25T04:45:12Z</time>
        </trkpt>
        <trkpt lat="46.02660368196666" lon="9.820341104641557">
            <ele>1501.0</ele>
            <time>2018-04-25T04:46:18Z</time>
        </trkpt>
        <trkpt lat="46.02661130949855" lon="9.821249954402447">
            <ele>1507.59997558594</ele>
            <time>2018-04-25T04:47:04Z</time>
        </trkpt>
        <trkpt lat="46.026401510462165" lon="9.821852697059512">
            <ele>1512.80004882812</ele>
            <time>2018-04-25T04:47:22Z</time>
        </trkpt>
        <trkpt lat="46.02653117850423" lon="9.822340942919254">
            <ele>1518.30004882812</ele>
            <time>2018-04-25T04:48:12Z</time>
        </trkpt>
        <trkpt lat="46.0260886978358" lon="9.824724169448018">
            <ele>1546.40002441406</ele>
            <time>2018-04-25T04:50:52Z</time>
        </trkpt>
        <trkpt lat="46.02637862786651" lon="9.825717005878687">
            <ele>1557.90002441406</ele>
            <time>2018-04-25T04:52:04Z</time>
        </trkpt>
        <trkpt lat="46.026443503797054" lon="9.827384920790792">
            <ele>1583.59997558594</ele>
            <time>2018-04-25T04:53:32Z</time>
        </trkpt>
        <trkpt lat="46.02602390572429" lon="9.82900908216834">
            <ele>1594.80004882812</ele>
            <time>2018-04-25T04:55:42Z</time>
        </trkpt>
        <trkpt lat="46.02585987187922" lon="9.829133050516248">
            <ele>1596.5</ele>
            <time>2018-04-25T04:55:58Z</time>
        </trkpt>
        <trkpt lat="46.02568821050227" lon="9.828565595671535">
            <ele>1600.59997558594</ele>
            <time>2018-04-25T04:56:32Z</time>
        </trkpt>
        <trkpt lat="46.02529903873801" lon="9.828483620658517">
            <ele>1602.80004882812</ele>
            <time>2018-04-25T04:56:58Z</time>
        </trkpt>
        <trkpt lat="46.02500533685088" lon="9.829572681337595">
            <ele>1606.59997558594</ele>
            <time>2018-04-25T04:57:58Z</time>
        </trkpt>
        <trkpt lat="46.02553557604551" lon="9.830336607992649">
            <ele>1609.80004882812</ele>
            <time>2018-04-25T04:58:38Z</time>
        </trkpt>
        <trkpt lat="46.02553943172097" lon="9.830916384235024">
            <ele>1612.90002441406</ele>
            <time>2018-04-25T04:59:04Z</time>
        </trkpt>
        <trkpt lat="46.02581787854433" lon="9.831665055826306">
            <ele>1617.09997558594</ele>
            <time>2018-04-25T04:59:46Z</time>
        </trkpt>
        <trkpt lat="46.02577588520944" lon="9.832476591691375">
            <ele>1621.30004882812</ele>
            <time>2018-04-25T05:00:24Z</time>
        </trkpt>
        <trkpt lat="46.02602005004883" lon="9.833210008218884">
            <ele>1627.69995117188</ele>
            <time>2018-04-25T05:01:08Z</time>
        </trkpt>
        <trkpt lat="46.026580799371004" lon="9.833907131105661">
            <ele>1630.90002441406</ele>
            <time>2018-04-25T05:01:56Z</time>
        </trkpt>
        <trkpt lat="46.026580799371004" lon="9.834197983145714">
            <ele>1631.40002441406</ele>
            <time>2018-04-25T05:02:16Z</time>
        </trkpt>
        <trkpt lat="46.02676771581173" lon="9.834354389458895">
            <ele>1631.5</ele>
            <time>2018-04-25T05:02:36Z</time>
        </trkpt>
        <trkpt lat="46.02717591449618" lon="9.83424567617476">
            <ele>1634.30004882812</ele>
            <time>2018-04-25T05:03:02Z</time>
        </trkpt>
        <trkpt lat="46.02690886706114" lon="9.836170161142945">
            <ele>1642.80004882812</ele>
            <time>2018-04-25T05:04:34Z</time>
        </trkpt>
        <trkpt lat="46.02782819420099" lon="9.837163919582963">
            <ele>1648.0</ele>
            <time>2018-04-25T05:05:38Z</time>
        </trkpt>
        <trkpt lat="46.02814486250281" lon="9.838093724101782">
            <ele>1651.69995117188</ele>
            <time>2018-04-25T05:06:32Z</time>
        </trkpt>
        <trkpt lat="46.028495812788606" lon="9.838270163163543">
            <ele>1654.40002441406</ele>
            <time>2018-04-25T05:06:50Z</time>
        </trkpt>
        <trkpt lat="46.028457675129175" lon="9.83853436075151">
            <ele>1654.30004882812</ele>
            <time>2018-04-25T05:07:02Z</time>
        </trkpt>
        <trkpt lat="46.02870938368142" lon="9.838994946330786">
            <ele>1656.19995117188</ele>
            <time>2018-04-25T05:07:26Z</time>
        </trkpt>
        <trkpt lat="46.02947616018355" lon="9.839092260226607">
            <ele>1658.0</ele>
            <time>2018-04-25T05:08:24Z</time>
        </trkpt>
        <trkpt lat="46.029956778511405" lon="9.839652087539434">
            <ele>1659.69995117188</ele>
            <time>2018-04-25T05:09:08Z</time>
        </trkpt>
        <trkpt lat="46.02941891178489" lon="9.840439818799496">
            <ele>1663.90002441406</ele>
            <time>2018-04-25T05:10:00Z</time>
        </trkpt>
        <trkpt lat="46.029262505471706" lon="9.840975757688284">
            <ele>1664.59997558594</ele>
            <time>2018-04-25T05:10:30Z</time>
        </trkpt>
        <trkpt lat="46.02933500893414" lon="9.841216066852212">
            <ele>1666.81994628906</ele>
            <time>2018-04-25T05:10:50Z</time>
        </trkpt>
        <trkpt lat="46.02879714220762" lon="9.841999020427465">
            <ele>1669.90002441406</ele>
            <time>2018-04-25T05:11:48Z</time>
        </trkpt>
        <trkpt lat="46.02637862786651" lon="9.842416774481535">
            <ele>1716.66003417969</ele>
            <time>2018-04-25T05:16:52Z</time>
        </trkpt>
        <trkpt lat="46.02600856684148" lon="9.843363761901855">
            <ele>1729.7099609375</ele>
            <time>2018-04-25T05:18:16Z</time>
        </trkpt>
        <trkpt lat="46.02605818770826" lon="9.843648914247751">
            <ele>1735.2900390625</ele>
            <time>2018-04-25T05:18:42Z</time>
        </trkpt>
        <trkpt lat="46.02587127126753" lon="9.843741450458765">
            <ele>1735.67004394531</ele>
            <time>2018-04-25T05:18:58Z</time>
        </trkpt>
        <trkpt lat="46.0255241766572" lon="9.84472087584436">
            <ele>1753.33996582031</ele>
            <time>2018-04-25T05:20:44Z</time>
        </trkpt>
        <trkpt lat="46.0248145647347" lon="9.845657385885715">
            <ele>1772.18005371094</ele>
            <time>2018-04-25T05:23:26Z</time>
        </trkpt>
        <trkpt lat="46.02445984259248" lon="9.845781354233623">
            <ele>1783.0</ele>
            <time>2018-04-25T05:24:26Z</time>
        </trkpt>
        <trkpt lat="46.02445221506059" lon="9.846582412719727">
            <ele>1792.09997558594</ele>
            <time>2018-04-25T05:25:44Z</time>
        </trkpt>
        <trkpt lat="46.02429580874741" lon="9.846780812367797">
            <ele>1794.40002441406</ele>
            <time>2018-04-25T05:25:54Z</time>
        </trkpt>
        <trkpt lat="46.023994479328394" lon="9.848335236310959">
            <ele>1814.19995117188</ele>
            <time>2018-04-25T05:27:46Z</time>
        </trkpt>
        <trkpt lat="46.02414325810969" lon="9.849095307290554">
            <ele>1829.10998535156</ele>
            <time>2018-04-25T05:29:12Z</time>
        </trkpt>
        <trkpt lat="46.02385709993541" lon="9.850056627765298">
            <ele>1841.85998535156</ele>
            <time>2018-04-25T05:30:38Z</time>
        </trkpt>
        <trkpt lat="46.02404024451971" lon="9.851050386205316">
            <ele>1853.4599609375</ele>
            <time>2018-04-25T05:32:08Z</time>
        </trkpt>
        <trkpt lat="46.023735059425235" lon="9.852580083534122">
            <ele>1867.19995117188</ele>
            <time>2018-04-25T05:34:24Z</time>
        </trkpt>
        <trkpt lat="46.02396011352539" lon="9.853953374549747">
            <ele>1878.92004394531</ele>
            <time>2018-04-25T05:36:02Z</time>
        </trkpt>
        <trkpt lat="46.02367781102657" lon="9.854963310062885">
            <ele>1888.59997558594</ele>
            <time>2018-04-25T05:37:18Z</time>
        </trkpt>
        <trkpt lat="46.02396011352539" lon="9.856283208355308">
            <ele>1894.19995117188</ele>
            <time>2018-04-25T05:39:00Z</time>
        </trkpt>
        <trkpt lat="46.023674039170146" lon="9.857871998101473">
            <ele>1910.0</ele>
            <time>2018-04-25T05:41:00Z</time>
        </trkpt>
        <trkpt lat="46.02382658980787" lon="9.860326806083322">
            <ele>1932.5</ele>
            <time>2018-04-25T05:44:52Z</time>
        </trkpt>
        <trkpt lat="46.023635901510715" lon="9.860475501045585">
            <ele>1937.38000488281</ele>
            <time>2018-04-25T05:45:38Z</time>
        </trkpt>
        <trkpt lat="46.02400210686028" lon="9.860496539622545">
            <ele>1939.28002929688</ele>
            <time>2018-04-25T05:46:12Z</time>
        </trkpt>
        <trkpt lat="46.02420042268932" lon="9.861293826252222">
            <ele>1939.90002441406</ele>
            <time>2018-04-25T06:02:17Z</time>
        </trkpt>
        <trkpt lat="46.02255245670676" lon="9.8618717584759">
            <ele>1961.7900390625</ele>
            <time>2018-04-25T06:05:04Z</time>
        </trkpt>
        <trkpt lat="46.02208709344268" lon="9.862356148660183">
            <ele>1965.80004882812</ele>
            <time>2018-04-25T06:08:26Z</time>
        </trkpt>
        <trkpt lat="46.02094271220267" lon="9.86250014975667">
            <ele>1984.31005859375</ele>
            <time>2018-04-25T06:11:58Z</time>
        </trkpt>
        <trkpt lat="46.02020267397165" lon="9.862352376803756">
            <ele>2000.93994140625</ele>
            <time>2018-04-25T06:14:14Z</time>
        </trkpt>
        <trkpt lat="46.01967243477702" lon="9.862704249098897">
            <ele>2022.93005371094</ele>
            <time>2018-04-25T06:17:10Z</time>
        </trkpt>
        <trkpt lat="46.019111601635814" lon="9.862770047038794">
            <ele>2037.22998046875</ele>
            <time>2018-04-25T06:19:56Z</time>
        </trkpt>
        <trkpt lat="46.01826477795839" lon="9.863343201577663">
            <ele>2084.17993164062</ele>
            <time>2018-04-25T06:25:18Z</time>
        </trkpt>
        <trkpt lat="46.017509484663606" lon="9.863452920690179">
            <ele>2112.38989257812</ele>
            <time>2018-04-25T06:28:20Z</time>
        </trkpt>
        <trkpt lat="46.01702878251672" lon="9.863833459094167">
            <ele>2124.4599609375</ele>
            <time>2018-04-25T06:29:48Z</time>
        </trkpt>
        <trkpt lat="46.01556396111846" lon="9.864275939762592">
            <ele>2156.60009765625</ele>
            <time>2018-04-25T06:35:08Z</time>
        </trkpt>
        <trkpt lat="46.01502223871648" lon="9.864610712975264">
            <ele>2164.35009765625</ele>
            <time>2018-04-25T06:36:52Z</time>
        </trkpt>
        <trkpt lat="46.01445386186242" lon="9.865283947438002">
            <ele>2201.60009765625</ele>
            <time>2018-04-25T06:42:24Z</time>
        </trkpt>
        <trkpt lat="46.012828862294555" lon="9.865356450900435">
            <ele>2281.39990234375</ele>
            <time>2018-04-25T06:58:42Z</time>
        </trkpt>
        <trkpt lat="46.01235964335501" lon="9.865765571594238">
            <ele>2295.35009765625</ele>
            <time>2018-04-25T07:01:32Z</time>
        </trkpt>
        <trkpt lat="46.01194381713867" lon="9.86580278724432">
            <ele>2336.40991210938</ele>
            <time>2018-04-25T07:12:32Z</time>
        </trkpt>
        <trkpt lat="46.009624460712075" lon="9.865290652960539">
            <ele>2418.67993164062</ele>
            <time>2018-04-25T07:35:49Z</time>
        </trkpt>
        <trkpt lat="46.009700736030936" lon="9.865866657346487">
            <ele>2549.0</ele>
            <time>2018-04-25T07:50:24Z</time>
        </trkpt>
        <trkpt lat="46.01035309955478" lon="9.866371164098382">
            <ele>2601.0</ele>
            <time>2018-04-25T07:55:22Z</time>
        </trkpt>
        <trkpt lat="46.01025394164026" lon="9.866622956469655">
            <ele>2601.10009765625</ele>
            <time>2018-04-25T08:16:17Z</time>
        </trkpt>
        <trkpt lat="46.010333988815546" lon="9.867438348010182">
            <ele>2582.8798828125</ele>
            <time>2018-04-25T08:17:59Z</time>
        </trkpt>
        <trkpt lat="46.010021176189184" lon="9.868702925741673">
            <ele>2570.43994140625</ele>
            <time>2018-04-25T08:21:45Z</time>
        </trkpt>
        <trkpt lat="46.0095558129251" lon="9.869528794661164">
            <ele>2550.39990234375</ele>
            <time>2018-04-25T08:29:01Z</time>
        </trkpt>
        <trkpt lat="46.00955966860056" lon="9.870856320485473">
            <ele>2533.51000976562</ele>
            <time>2018-04-25T08:34:19Z</time>
        </trkpt>
        <trkpt lat="46.009189607575536" lon="9.871757542714477">
            <ele>2525.669921875</ele>
            <time>2018-04-25T08:36:27Z</time>
        </trkpt>
        <trkpt lat="46.00870898924768" lon="9.873919486999512">
            <ele>2497.35009765625</ele>
            <time>2018-04-25T08:52:15Z</time>
        </trkpt>
        <trkpt lat="46.00846859626472" lon="9.875853527337313">
            <ele>2463.57006835938</ele>
            <time>2018-04-25T09:08:59Z</time>
        </trkpt>
        <trkpt lat="46.00904845632613" lon="9.876489629969">
            <ele>2473.5</ele>
            <time>2018-04-25T09:13:55Z</time>
        </trkpt>
        <trkpt lat="46.00959780625999" lon="9.876545872539282">
            <ele>2455.56005859375</ele>
            <time>2018-04-25T09:18:37Z</time>
        </trkpt>
        <trkpt lat="46.009700736030936" lon="9.87745857797563">
            <ele>2377.03002929688</ele>
            <time>2018-04-25T09:29:35Z</time>
        </trkpt>
        <trkpt lat="46.009388007223606" lon="9.878423670306802">
            <ele>2359.89990234375</ele>
            <time>2018-04-25T09:33:01Z</time>
        </trkpt>
        <trkpt lat="46.00943754427135" lon="9.878976792097092">
            <ele>2361.30004882812</ele>
            <time>2018-04-25T09:37:09Z</time>
        </trkpt>
        <trkpt lat="46.0098113771528" lon="9.879892347380519">
            <ele>2349.89990234375</ele>
            <time>2018-04-25T09:40:17Z</time>
        </trkpt>
        <trkpt lat="46.009941129013896" lon="9.880679156631231">
            <ele>2333.05004882812</ele>
            <time>2018-04-25T09:43:53Z</time>
        </trkpt>
        <trkpt lat="46.010890966281295" lon="9.882014309987426">
            <ele>2323.3701171875</ele>
            <time>2018-04-25T09:51:15Z</time>
        </trkpt>
        <trkpt lat="46.01090622134507" lon="9.882560726255178">
            <ele>2318.0</ele>
            <time>2018-04-25T09:52:31Z</time>
        </trkpt>
        <trkpt lat="46.0112342890352" lon="9.88283732905984">
            <ele>2321.02001953125</ele>
            <time>2018-04-25T09:53:55Z</time>
        </trkpt>
        <trkpt lat="46.011028261855245" lon="9.884125711396337">
            <ele>2361.9599609375</ele>
            <time>2018-04-25T10:04:05Z</time>
        </trkpt>
        <trkpt lat="46.010734559968114" lon="9.884659806266427">
            <ele>2374.7099609375</ele>
            <time>2018-04-25T10:08:18Z</time>
        </trkpt>
        <trkpt lat="46.0107955802232" lon="9.884925847873092">
            <ele>2437.14990234375</ele>
            <time>2018-04-25T10:14:37Z</time>
        </trkpt>
        <trkpt lat="46.012432062998414" lon="9.887179406359792">
            <ele>2480.73999023438</ele>
            <time>2018-04-25T11:32:10Z</time>
        </trkpt>
        <trkpt lat="46.01351550780237" lon="9.88793084397912">
            <ele>2399.78002929688</ele>
            <time>2018-04-25T11:41:50Z</time>
        </trkpt>
        <trkpt lat="46.014385214075446" lon="9.888040563091636">
            <ele>2299.05004882812</ele>
            <time>2018-04-25T11:53:54Z</time>
        </trkpt>
        <trkpt lat="46.0164909157902" lon="9.885339746251702">
            <ele>2187.419921875</ele>
            <time>2018-04-25T12:01:14Z</time>
        </trkpt>
        <trkpt lat="46.01680758409202" lon="9.884642623364925">
            <ele>2174.18994140625</ele>
            <time>2018-04-25T12:02:10Z</time>
        </trkpt>
        <trkpt lat="46.017253836616874" lon="9.882346149533987">
            <ele>2123.94995117188</ele>
            <time>2018-04-25T12:05:07Z</time>
        </trkpt>
        <trkpt lat="46.01775356568396" lon="9.880902282893658">
            <ele>2099.60009765625</ele>
            <time>2018-04-25T12:07:35Z</time>
        </trkpt>
        <trkpt lat="46.01807400584221" lon="9.880230892449617">
            <ele>2084.60009765625</ele>
            <time>2018-04-25T12:08:29Z</time>
        </trkpt>
        <trkpt lat="46.01840207353234" lon="9.879940040409565">
            <ele>2077.0</ele>
            <time>2018-04-25T12:09:31Z</time>
        </trkpt>
        <trkpt lat="46.019782992079854" lon="9.877111399546266">
            <ele>2063.30004882812</ele>
            <time>2018-04-25T12:14:57Z</time>
        </trkpt>
        <trkpt lat="46.02050014771521" lon="9.87675097770989">
            <ele>2054.69995117188</ele>
            <time>2018-04-25T12:16:35Z</time>
        </trkpt>
        <trkpt lat="46.020870208740234" lon="9.876825325191021">
            <ele>2049.05004882812</ele>
            <time>2018-04-25T12:17:27Z</time>
        </trkpt>
        <trkpt lat="46.02112200111151" lon="9.877212485298514">
            <ele>2037.91003417969</ele>
            <time>2018-04-25T12:18:07Z</time>
        </trkpt>
        <trkpt lat="46.02183152921498" lon="9.877505265176296">
            <ele>2028.39001464844</ele>
            <time>2018-04-25T12:19:41Z</time>
        </trkpt>
        <trkpt lat="46.02233888581395" lon="9.8782872967422">
            <ele>2010.68005371094</ele>
            <time>2018-04-25T12:21:13Z</time>
        </trkpt>
        <trkpt lat="46.02321621961892" lon="9.877758985385299">
            <ele>1997.52001953125</ele>
            <time>2018-04-25T12:22:53Z</time>
        </trkpt>
        <trkpt lat="46.02349475026131" lon="9.876975025981665">
            <ele>2014.69995117188</ele>
            <time>2015-03-21T14:23:19Z</time>
        </trkpt>
        <trkpt lat="46.0236091632396" lon="9.875669460743666">
            <ele>2011.69995117188</ele>
            <time>2015-03-21T14:50:28Z</time>
        </trkpt>
        <trkpt lat="46.02344898506999" lon="9.874963788315654">
            <ele>2000.16003417969</ele>
            <time>2015-03-21T14:51:14Z</time>
        </trkpt>
        <trkpt lat="46.02351000532508" lon="9.872641582041979">
            <ele>1988.5</ele>
            <time>2015-03-21T14:53:18Z</time>
        </trkpt>
        <trkpt lat="46.02385709993541" lon="9.870177302509546">
            <ele>1971.90002441406</ele>
            <time>2015-03-21T14:55:45Z</time>
        </trkpt>
        <trkpt lat="46.02420042268932" lon="9.869308434426785">
            <ele>1969.69995117188</ele>
            <time>2015-03-21T14:56:47Z</time>
        </trkpt>
        <trkpt lat="46.02435305714607" lon="9.866261444985867">
            <ele>1965.80004882812</ele>
            <time>2015-03-21T15:00:01Z</time>
        </trkpt>
        <trkpt lat="46.02419665083289" lon="9.864481966942549">
            <ele>1964.80004882812</ele>
            <time>2015-03-21T15:01:53Z</time>
        </trkpt>
        <trkpt lat="46.02447895333171" lon="9.863425260409713">
            <ele>1964.19995117188</ele>
            <time>2015-03-21T15:03:05Z</time>
        </trkpt>
        <trkpt lat="46.02444073185325" lon="9.862900720909238">
            <ele>1968.90002441406</ele>
            <time>2015-03-21T15:03:43Z</time>
        </trkpt>
        <trkpt lat="46.02426144294441" lon="9.862862583249807">
            <ele>1971.19995117188</ele>
            <time>2015-03-21T15:04:08Z</time>
        </trkpt>
        <trkpt lat="46.02418516762555" lon="9.861332885921001">
            <ele>1962.90002441406</ele>
            <time>2015-03-21T15:06:14Z</time>
        </trkpt>
        <trkpt lat="46.02376556955278" lon="9.860138883814216">
            <ele>1941.0400390625</ele>
            <time>2015-03-21T15:07:59Z</time>
        </trkpt>
        <trkpt lat="46.023696921765804" lon="9.857881553471088">
            <ele>1914.11999511719</ele>
            <time>2015-03-21T15:10:45Z</time>
        </trkpt>
        <trkpt lat="46.023891465738416" lon="9.856227887794375">
            <ele>1902.10998535156</ele>
            <time>2015-03-21T15:12:30Z</time>
        </trkpt>
        <trkpt lat="46.02380756288767" lon="9.85509012825787">
            <ele>1897.78002929688</ele>
            <time>2015-03-21T15:13:34Z</time>
        </trkpt>
        <trkpt lat="46.02398299612105" lon="9.854305246844888">
            <ele>1888.65002441406</ele>
            <time>2015-03-21T15:14:18Z</time>
        </trkpt>
        <trkpt lat="46.02378082461655" lon="9.852663986384869">
            <ele>1877.58996582031</ele>
            <time>2015-03-21T15:15:46Z</time>
        </trkpt>
        <trkpt lat="46.02447895333171" lon="9.845813792198896">
            <ele>1792.52001953125</ele>
            <time>2015-03-21T15:22:52Z</time>
        </trkpt>
        <trkpt lat="46.024562856182456" lon="9.845640202984214">
            <ele>1790.10998535156</ele>
            <time>2015-03-21T15:23:06Z</time>
        </trkpt>
        <trkpt lat="46.02487566880882" lon="9.845729805529118">
            <ele>1781.93994140625</ele>
            <time>2015-03-21T15:23:41Z</time>
        </trkpt>
        <trkpt lat="46.02511212229729" lon="9.845191016793251">
            <ele>1772.32995605469</ele>
            <time>2015-03-21T15:24:21Z</time>
        </trkpt>
        <trkpt lat="46.025554686784744" lon="9.844807628542185">
            <ele>1760.7900390625</ele>
            <time>2015-03-21T15:25:08Z</time>
        </trkpt>
        <trkpt lat="46.02613069117069" lon="9.843442887067795">
            <ele>1737.23999023438</ele>
            <time>2015-03-21T15:26:48Z</time>
        </trkpt>
        <trkpt lat="46.026325235143304" lon="9.842540742829442">
            <ele>1724.30004882812</ele>
            <time>2015-03-21T15:27:46Z</time>
        </trkpt>
        <trkpt lat="46.02694700472057" lon="9.842251818627119">
            <ele>1711.28002929688</ele>
            <time>2015-03-21T15:28:45Z</time>
        </trkpt>
        <trkpt lat="46.02833177894354" lon="9.842239413410425">
            <ele>1688.68994140625</ele>
            <time>2015-03-21T15:30:48Z</time>
        </trkpt>
        <trkpt lat="46.02876277640462" lon="9.842006647959352">
            <ele>1682.43994140625</ele>
            <time>2015-03-21T15:31:21Z</time>
        </trkpt>
        <trkpt lat="46.029129065573215" lon="9.841669108718634">
            <ele>1676.68005371094</ele>
            <time>2015-03-21T15:32:01Z</time>
        </trkpt>
        <trkpt lat="46.02968981489539" lon="9.83989717438817">
            <ele>1657.93005371094</ele>
            <time>2015-03-21T15:33:56Z</time>
        </trkpt>
        <trkpt lat="46.0296287946403" lon="9.839317314326763">
            <ele>1654.56994628906</ele>
            <time>2015-03-21T15:34:29Z</time>
        </trkpt>
        <trkpt lat="46.029327381402254" lon="9.839057894423604">
            <ele>1651.68005371094</ele>
            <time>2015-03-21T15:35:01Z</time>
        </trkpt>
        <trkpt lat="46.02850721217692" lon="9.838897716253996">
            <ele>1651.69995117188</ele>
            <time>2015-03-21T15:36:17Z</time>
        </trkpt>
        <trkpt lat="46.02709578350186" lon="9.836146356537938">
            <ele>1646.88000488281</ele>
            <time>2015-03-21T15:41:21Z</time>
        </trkpt>
        <trkpt lat="46.02705001831055" lon="9.83432773500681">
            <ele>1639.90002441406</ele>
            <time>2015-03-21T15:42:51Z</time>
        </trkpt>
        <trkpt lat="46.02692412212491" lon="9.834197983145714">
            <ele>1639.18994140625</ele>
            <time>2015-03-21T15:43:07Z</time>
        </trkpt>
        <trkpt lat="46.02658465504646" lon="9.834374422207475">
            <ele>1637.73999023438</ele>
            <time>2015-03-21T15:43:36Z</time>
        </trkpt>
        <trkpt lat="46.025890382006764" lon="9.833463644608855">
            <ele>1628.60998535156</ele>
            <time>2015-03-21T15:44:48Z</time>
        </trkpt>
        <trkpt lat="46.0259819123894" lon="9.832865679636598">
            <ele>1625.72998046875</ele>
            <time>2015-03-21T15:45:18Z</time>
        </trkpt>
        <trkpt lat="46.02581787854433" lon="9.831929169595242">
            <ele>1620.92004394531</ele>
            <time>2015-03-21T15:46:08Z</time>
        </trkpt>
        <trkpt lat="46.02500919252634" lon="9.829864539206028">
            <ele>1610.34997558594</ele>
            <time>2015-03-21T15:48:08Z</time>
        </trkpt>
        <trkpt lat="46.025371542200446" lon="9.828783022239804">
            <ele>1608.80004882812</ele>
            <time>2015-03-21T15:49:34Z</time>
        </trkpt>
        <trkpt lat="46.0255965963006" lon="9.828645726665854">
            <ele>1607.4599609375</ele>
            <time>2015-03-21T15:50:09Z</time>
        </trkpt>
        <trkpt lat="46.02601242251694" lon="9.829231286421418">
            <ele>1605.69995117188</ele>
            <time>2015-03-21T15:50:51Z</time>
        </trkpt>
        <trkpt lat="46.02619171142578" lon="9.829045291990042">
            <ele>1601.68994140625</ele>
            <time>2015-03-21T15:51:12Z</time>
        </trkpt>
        <trkpt lat="46.02655028924346" lon="9.827476534992456">
            <ele>1581.51000976562</ele>
            <time>2015-03-21T15:52:49Z</time>
        </trkpt>
        <trkpt lat="46.02611158043146" lon="9.824856771156192">
            <ele>1563.23999023438</ele>
            <time>2015-03-21T15:55:13Z</time>
        </trkpt>
        <trkpt lat="46.02645875886083" lon="9.82254596427083">
            <ele>1536.31994628906</ele>
            <time>2015-03-21T15:57:35Z</time>
        </trkpt>
        <trkpt lat="46.02667995728552" lon="9.821882285177708">
            <ele>1526.7099609375</ele>
            <time>2015-03-21T15:58:15Z</time>
        </trkpt>
        <trkpt lat="46.02664944715798" lon="9.821488419547677">
            <ele>1523.34997558594</ele>
            <time>2015-03-21T16:03:46Z</time>
        </trkpt>
        <trkpt lat="46.02589800953865" lon="9.818227775394917">
            <ele>1488.26000976562</ele>
            <time>2015-03-21T16:06:57Z</time>
        </trkpt>
        <trkpt lat="46.02521136403084" lon="9.817221611738205">
            <ele>1480.08996582031</ele>
            <time>2015-03-21T16:07:55Z</time>
        </trkpt>
        <trkpt lat="46.02496719919145" lon="9.816270852461457">
            <ele>1476.23999023438</ele>
            <time>2015-03-21T16:08:51Z</time>
        </trkpt>
        <trkpt lat="46.02500919252634" lon="9.815923674032092">
            <ele>1472.88000488281</ele>
            <time>2015-03-21T16:09:13Z</time>
        </trkpt>
        <trkpt lat="46.02529903873801" lon="9.816236486658454">
            <ele>1464.22998046875</ele>
            <time>2015-03-21T16:09:59Z</time>
        </trkpt>
        <trkpt lat="46.02539828047156" lon="9.815954184159636">
            <ele>1459.42004394531</ele>
            <time>2015-03-21T16:10:14Z</time>
        </trkpt>
        <trkpt lat="46.02560807950795" lon="9.814988169819117">
            <ele>1445.5</ele>
            <time>2015-03-21T16:11:19Z</time>
        </trkpt>
        <trkpt lat="46.0253066662699" lon="9.815285643562675">
            <ele>1435.86999511719</ele>
            <time>2015-03-21T16:11:58Z</time>
        </trkpt>
        <trkpt lat="46.02582165040076" lon="9.813270550221205">
            <ele>1403.66003417969</ele>
            <time>2015-03-21T16:14:13Z</time>
        </trkpt>
        <trkpt lat="46.025436418130994" lon="9.811889631673694">
            <ele>1382.98999023438</ele>
            <time>2015-03-21T16:15:45Z</time>
        </trkpt>
        <trkpt lat="46.025375397875905" lon="9.81106661260128">
            <ele>1372.42004394531</ele>
            <time>2015-03-21T16:16:32Z</time>
        </trkpt>
        <trkpt lat="46.025588968768716" lon="9.81009959243238">
            <ele>1359.92004394531</ele>
            <time>2015-03-21T16:17:28Z</time>
        </trkpt>
        <trkpt lat="46.02630612440407" lon="9.808686235919595">
            <ele>1336.36999511719</ele>
            <time>2015-03-21T16:19:07Z</time>
        </trkpt>
        <trkpt lat="46.02656554430723" lon="9.806830398738384">
            <ele>1319.55004882812</ele>
            <time>2015-03-21T16:20:54Z</time>
        </trkpt>
        <trkpt lat="46.0264740139246" lon="9.806077033281326">
            <ele>1313.78002929688</ele>
            <time>2015-03-21T16:21:33Z</time>
        </trkpt>
        <trkpt lat="46.025829277932644" lon="9.805065169930458">
            <ele>1302.71997070312</ele>
            <time>2015-03-21T16:22:44Z</time>
        </trkpt>
        <trkpt lat="46.026046788319945" lon="9.803150156512856">
            <ele>1288.30004882812</ele>
            <time>2015-03-21T16:24:28Z</time>
        </trkpt>
        <trkpt lat="46.02569583803415" lon="9.802664760500193">
            <ele>1282.06005859375</ele>
            <time>2015-03-21T16:25:02Z</time>
        </trkpt>
        <trkpt lat="46.02554705925286" lon="9.800631562247872">
            <ele>1254.66003417969</ele>
            <time>2015-03-21T16:26:56Z</time>
        </trkpt>
        <trkpt lat="46.02483367547393" lon="9.798701293766499">
            <ele>1231.58996582031</ele>
            <time>2015-03-21T16:28:57Z</time>
        </trkpt>
        <trkpt lat="46.02496334351599" lon="9.798137694597244">
            <ele>1226.30004882812</ele>
            <time>2015-03-21T16:29:21Z</time>
        </trkpt>
        <trkpt lat="46.02483753114939" lon="9.797468148171902">
            <ele>1216.68994140625</ele>
            <time>2015-03-21T16:30:03Z</time>
        </trkpt>
        <trkpt lat="46.02506635710597" lon="9.79680153541267">
            <ele>1212.09997558594</ele>
            <time>2015-03-21T16:30:42Z</time>
        </trkpt>
        <trkpt lat="46.025035846978426" lon="9.795506447553635">
            <ele>1209.47998046875</ele>
            <time>2015-03-21T16:31:51Z</time>
        </trkpt>
        <trkpt lat="46.02488706819713" lon="9.794974364340305">
            <ele>1204.67004394531</ele>
            <time>2015-03-21T16:32:21Z</time>
        </trkpt>
        <trkpt lat="46.024959571659565" lon="9.794324850663543">
            <ele>1199.38000488281</ele>
            <time>2015-03-21T16:32:56Z</time>
        </trkpt>
        <trkpt lat="46.024330174550414" lon="9.792083781212568">
            <ele>1185.5</ele>
            <time>2015-03-21T16:35:05Z</time>
        </trkpt>
        <trkpt lat="46.024387339130044" lon="9.791354220360518">
            <ele>1181.59997558594</ele>
            <time>2015-03-21T16:35:45Z</time>
        </trkpt>
        <trkpt lat="46.024127919226885" lon="9.788805032148957">
            <ele>1168.14001464844</ele>
            <time>2015-03-21T16:37:55Z</time>
        </trkpt>
        <trkpt lat="46.023635901510715" lon="9.78741648606956">
            <ele>1162.0</ele>
            <time>2015-03-21T16:39:18Z</time>
        </trkpt>
    </trkseg>
</trk>
